[{"login": "0101", "id": 217092, "node_id": "MDQ6VXNlcjIxNzA5Mg==", "avatar_url": "https://avatars.githubusercontent.com/u/217092?v=4", "gravatar_id": "", "url": "https://api.github.com/users/0101", "html_url": "https://github.com/0101", "followers_url": "https://api.github.com/users/0101/followers", "following_url": "https://api.github.com/users/0101/following{/other_user}", "gists_url": "https://api.github.com/users/0101/gists{/gist_id}", "starred_url": "https://api.github.com/users/0101/starred{/owner}{/repo}", "subscriptions_url": "https://api.github.com/users/0101/subscriptions", "organizations_url": "https://api.github.com/users/0101/orgs", "repos_url": "https://api.github.com/users/0101/repos", "events_url": "https://api.github.com/users/0101/events{/privacy}", "received_events_url": "https://api.github.com/users/0101/received_events", "type": "User", "user_view_type": "public", "site_admin": false}, {"login": "04diiguyi", "id": 22650810, "node_id": "MDQ6VXNlcjIyNjUwODEw", "avatar_url": "https://avatars.githubusercontent.com/u/22650810?v=4", "gravatar_id": "", "url": "https://api.github.com/users/04diiguyi", "html_url": "https://github.com/04diiguyi", "followers_url": "https://api.github.com/users/04diiguyi/followers", "following_url": "https://api.github.com/users/04diiguyi/following{/other_user}", "gists_url": "https://api.github.com/users/04diiguyi/gists{/gist_id}", "starred_url": "https://api.github.com/users/04diiguyi/starred{/owner}{/repo}", "subscriptions_url": "https://api.github.com/users/04diiguyi/subscriptions", "organizations_url": "https://api.github.com/users/04diiguyi/orgs", "repos_url": "https://api.github.com/users/04diiguyi/repos", "events_url": "https://api.github.com/users/04diiguyi/events{/privacy}", "received_events_url": "https://api.github.com/users/04diiguyi/received_events", "type": "User", "user_view_type": "public", "site_admin": false}, {"login": "13thsymphony", "id": 3278391, "node_id": "MDQ6VXNlcjMyNzgzOTE=", "avatar_url": "https://avatars.githubusercontent.com/u/3278391?v=4", "gravatar_id": "", "url": "https://api.github.com/users/13thsymphony", "html_url": "https://github.com/13thsymphony", "followers_url": "https://api.github.com/users/13thsymphony/followers", "following_url": "https://api.github.com/users/13thsymphony/following{/other_user}", "gists_url": "https://api.github.com/users/13thsymphony/gists{/gist_id}", "starred_url": "https://api.github.com/users/13thsymphony/starred{/owner}{/repo}", "subscriptions_url": "https://api.github.com/users/13thsymphony/subscriptions", "organizations_url": "https://api.github.com/users/13thsymphony/orgs", "repos_url": "https://api.github.com/users/13thsymphony/repos", "events_url": "https://api.github.com/users/13thsymphony/events{/privacy}", "received_events_url": "https://api.github.com/users/13thsymphony/received_events", "type": "User", "user_view_type": "public", "site_admin": false}, {"login": "2258093686", "id": 83654272, "node_id": "MDQ6VXNlcjgzNjU0Mjcy", "avatar_url": "https://avatars.githubusercontent.com/u/83654272?v=4", "gravatar_id": "", "url": "https://api.github.com/users/2258093686", "html_url": "https://github.com/2258093686", "followers_url": "https://api.github.com/users/2258093686/followers", "following_url": "https://api.github.com/users/2258093686/following{/other_user}", "gists_url": "https://api.github.com/users/2258093686/gists{/gist_id}", "starred_url": "https://api.github.com/users/2258093686/starred{/owner}{/repo}", "subscriptions_url": "https://api.github.com/users/2258093686/subscriptions", "organizations_url": "https://api.github.com/users/2258093686/orgs", "repos_url": "https://api.github.com/users/2258093686/repos", "events_url": "https://api.github.com/users/2258093686/events{/privacy}", "received_events_url": "https://api.github.com/users/2258093686/received_events", "type": "User", "user_view_type": "public", "site_admin": false}, {"login": "247arjun", "id": 20020129, "node_id": "MDQ6VXNlcjIwMDIwMTI5", "avatar_url": "https://avatars.githubusercontent.com/u/20020129?v=4", "gravatar_id": "", "url": "https://api.github.com/users/247arjun", "html_url": "https://github.com/247arjun", "followers_url": "https://api.github.com/users/247arjun/followers", "following_url": "https://api.github.com/users/247arjun/following{/other_user}", "gists_url": "https://api.github.com/users/247arjun/gists{/gist_id}", "starred_url": "https://api.github.com/users/247arjun/starred{/owner}{/repo}", "subscriptions_url": "https://api.github.com/users/247arjun/subscriptions", "organizations_url": "https://api.github.com/users/247arjun/orgs", "repos_url": "https://api.github.com/users/247arjun/repos", "events_url": "https://api.github.com/users/247arjun/events{/privacy}", "received_events_url": "https://api.github.com/users/247arjun/received_events", "type": "User", "user_view_type": "public", "site_admin": false}, {"login": "2percentsilk", "id": 3174849, "node_id": "MDQ6VXNlcjMxNzQ4NDk=", "avatar_url": "https://avatars.githubusercontent.com/u/3174849?v=4", "gravatar_id": "", "url": "https://api.github.com/users/2percentsilk", "html_url": "https://github.com/2percentsilk", "followers_url": "https://api.github.com/users/2percentsilk/followers", "following_url": "https://api.github.com/users/2percentsilk/following{/other_user}", "gists_url": "https://api.github.com/users/2percentsilk/gists{/gist_id}", "starred_url": "https://api.github.com/users/2percentsilk/starred{/owner}{/repo}", "subscriptions_url": "https://api.github.com/users/2percentsilk/subscriptions", "organizations_url": "https://api.github.com/users/2percentsilk/orgs", "repos_url": "https://api.github.com/users/2percentsilk/repos", "events_url": "https://api.github.com/users/2percentsilk/events{/privacy}", "received_events_url": "https://api.github.com/users/2percentsilk/received_events", "type": "User", "user_view_type": "public", "site_admin": true}, {"login": "4416km", "id": 26922859, "node_id": "MDQ6VXNlcjI2OTIyODU5", "avatar_url": "https://avatars.githubusercontent.com/u/26922859?v=4", "gravatar_id": "", "url": "https://api.github.com/users/4416km", "html_url": "https://github.com/4416km", "followers_url": "https://api.github.com/users/4416km/followers", "following_url": "https://api.github.com/users/4416km/following{/other_user}", "gists_url": "https://api.github.com/users/4416km/gists{/gist_id}", "starred_url": "https://api.github.com/users/4416km/starred{/owner}{/repo}", "subscriptions_url": "https://api.github.com/users/4416km/subscriptions", "organizations_url": "https://api.github.com/users/4416km/orgs", "repos_url": "https://api.github.com/users/4416km/repos", "events_url": "https://api.github.com/users/4416km/events{/privacy}", "received_events_url": "https://api.github.com/users/4416km/received_events", "type": "User", "user_view_type": "public", "site_admin": false}, {"login": "8ggmaker", "id": 3711046, "node_id": "MDQ6VXNlcjM3MTEwNDY=", "avatar_url": "https://avatars.githubusercontent.com/u/3711046?v=4", "gravatar_id": "", "url": "https://api.github.com/users/8ggmaker", "html_url": "https://github.com/8ggmaker", "followers_url": "https://api.github.com/users/8ggmaker/followers", "following_url": "https://api.github.com/users/8ggmaker/following{/other_user}", "gists_url": "https://api.github.com/users/8ggmaker/gists{/gist_id}", "starred_url": "https://api.github.com/users/8ggmaker/starred{/owner}{/repo}", "subscriptions_url": "https://api.github.com/users/8ggmaker/subscriptions", "organizations_url": "https://api.github.com/users/8ggmaker/orgs", "repos_url": "https://api.github.com/users/8ggmaker/repos", "events_url": "https://api.github.com/users/8ggmaker/events{/privacy}", "received_events_url": "https://api.github.com/users/8ggmaker/received_events", "type": "User", "user_view_type": "public", "site_admin": false}, {"login": "8Gitbrix", "id": 11791254, "node_id": "MDQ6VXNlcjExNzkxMjU0", "avatar_url": "https://avatars.githubusercontent.com/u/11791254?v=4", "gravatar_id": "", "url": "https://api.github.com/users/8Gitbrix", "html_url": "https://github.com/8Gitbrix", "followers_url": "https://api.github.com/users/8Gitbrix/followers", "following_url": "https://api.github.com/users/8Gitbrix/following{/other_user}", "gists_url": "https://api.github.com/users/8Gitbrix/gists{/gist_id}", "starred_url": "https://api.github.com/users/8Gitbrix/starred{/owner}{/repo}", "subscriptions_url": "https://api.github.com/users/8Gitbrix/subscriptions", "organizations_url": "https://api.github.com/users/8Gitbrix/orgs", "repos_url": "https://api.github.com/users/8Gitbrix/repos", "events_url": "https://api.github.com/users/8Gitbrix/events{/privacy}", "received_events_url": "https://api.github.com/users/8Gitbrix/received_events", "type": "User", "user_view_type": "public", "site_admin": false}, {"login": "a-hamad", "id": 147458435, "node_id": "U_kgDOCMoJgw", "avatar_url": "https://avatars.githubusercontent.com/u/147458435?v=4", "gravatar_id": "", "url": "https://api.github.com/users/a-hamad", "html_url": "https://github.com/a-hamad", "followers_url": "https://api.github.com/users/a-hamad/followers", "following_url": "https://api.github.com/users/a-hamad/following{/other_user}", "gists_url": "https://api.github.com/users/a-hamad/gists{/gist_id}", "starred_url": "https://api.github.com/users/a-hamad/starred{/owner}{/repo}", "subscriptions_url": "https://api.github.com/users/a-hamad/subscriptions", "organizations_url": "https://api.github.com/users/a-hamad/orgs", "repos_url": "https://api.github.com/users/a-hamad/repos", "events_url": "https://api.github.com/users/a-hamad/events{/privacy}", "received_events_url": "https://api.github.com/users/a-hamad/received_events", "type": "User", "user_view_type": "public", "site_admin": false}, {"login": "a-santamaria", "id": 7062665, "node_id": "MDQ6VXNlcjcwNjI2NjU=", "avatar_url": "https://avatars.githubusercontent.com/u/7062665?v=4", "gravatar_id": "", "url": "https://api.github.com/users/a-santamaria", "html_url": "https://github.com/a-santamaria", "followers_url": "https://api.github.com/users/a-santamaria/followers", "following_url": "https://api.github.com/users/a-santamaria/following{/other_user}", "gists_url": "https://api.github.com/users/a-santamaria/gists{/gist_id}", "starred_url": "https://api.github.com/users/a-santamaria/starred{/owner}{/repo}", "subscriptions_url": "https://api.github.com/users/a-santamaria/subscriptions", "organizations_url": "https://api.github.com/users/a-santamaria/orgs", "repos_url": "https://api.github.com/users/a-santamaria/repos", "events_url": "https://api.github.com/users/a-santamaria/events{/privacy}", "received_events_url": "https://api.github.com/users/a-santamaria/received_events", "type": "User", "user_view_type": "public", "site_admin": false}, {"login": "a0x1ab", "id": 59631311, "node_id": "MDQ6VXNlcjU5NjMxMzEx", "avatar_url": "https://avatars.githubusercontent.com/u/59631311?v=4", "gravatar_id": "", "url": "https://api.github.com/users/a0x1ab", "html_url": "https://github.com/a0x1ab", "followers_url": "https://api.github.com/users/a0x1ab/followers", "following_url": "https://api.github.com/users/a0x1ab/following{/other_user}", "gists_url": "https://api.github.com/users/a0x1ab/gists{/gist_id}", "starred_url": "https://api.github.com/users/a0x1ab/starred{/owner}{/repo}", "subscriptions_url": "https://api.github.com/users/a0x1ab/subscriptions", "organizations_url": "https://api.github.com/users/a0x1ab/orgs", "repos_url": "https://api.github.com/users/a0x1ab/repos", "events_url": "https://api.github.com/users/a0x1ab/events{/privacy}", "received_events_url": "https://api.github.com/users/a0x1ab/received_events", "type": "User", "user_view_type": "public", "site_admin": false}, {"login": "aainav269", "id": 183866862, "node_id": "U_kgDOCvWV7g", "avatar_url": "https://avatars.githubusercontent.com/u/183866862?v=4", "gravatar_id": "", "url": "https://api.github.com/users/aainav269", "html_url": "https://github.com/aainav269", "followers_url": "https://api.github.com/users/aainav269/followers", "following_url": "https://api.github.com/users/aainav269/following{/other_user}", "gists_url": "https://api.github.com/users/aainav269/gists{/gist_id}", "starred_url": "https://api.github.com/users/aainav269/starred{/owner}{/repo}", "subscriptions_url": "https://api.github.com/users/aainav269/subscriptions", "organizations_url": "https://api.github.com/users/aainav269/orgs", "repos_url": "https://api.github.com/users/aainav269/repos", "events_url": "https://api.github.com/users/aainav269/events{/privacy}", "received_events_url": "https://api.github.com/users/aainav269/received_events", "type": "User", "user_view_type": "public", "site_admin": false}, {"login": "aakash049", "id": 24788015, "node_id": "MDQ6VXNlcjI0Nzg4MDE1", "avatar_url": "https://avatars.githubusercontent.com/u/24788015?v=4", "gravatar_id": "", "url": "https://api.github.com/users/aakash049", "html_url": "https://github.com/aakash049", "followers_url": "https://api.github.com/users/aakash049/followers", "following_url": "https://api.github.com/users/aakash049/following{/other_user}", "gists_url": "https://api.github.com/users/aakash049/gists{/gist_id}", "starred_url": "https://api.github.com/users/aakash049/starred{/owner}{/repo}", "subscriptions_url": "https://api.github.com/users/aakash049/subscriptions", "organizations_url": "https://api.github.com/users/aakash049/orgs", "repos_url": "https://api.github.com/users/aakash049/repos", "events_url": "https://api.github.com/users/aakash049/events{/privacy}", "received_events_url": "https://api.github.com/users/aakash049/received_events", "type": "User", "user_view_type": "public", "site_admin": false}, {"login": "aamarsh", "id": 38086490, "node_id": "MDQ6VXNlcjM4MDg2NDkw", "avatar_url": "https://avatars.githubusercontent.com/u/38086490?v=4", "gravatar_id": "", "url": "https://api.github.com/users/aamarsh", "html_url": "https://github.com/aamarsh", "followers_url": "https://api.github.com/users/aamarsh/followers", "following_url": "https://api.github.com/users/aamarsh/following{/other_user}", "gists_url": "https://api.github.com/users/aamarsh/gists{/gist_id}", "starred_url": "https://api.github.com/users/aamarsh/starred{/owner}{/repo}", "subscriptions_url": "https://api.github.com/users/aamarsh/subscriptions", "organizations_url": "https://api.github.com/users/aamarsh/orgs", "repos_url": "https://api.github.com/users/aamarsh/repos", "events_url": "https://api.github.com/users/aamarsh/events{/privacy}", "received_events_url": "https://api.github.com/users/aamarsh/received_events", "type": "User", "user_view_type": "public", "site_admin": false}, {"login": "aandukuria", "id": 102808825, "node_id": "U_kgDOBiC8-Q", "avatar_url": "https://avatars.githubusercontent.com/u/102808825?v=4", "gravatar_id": "", "url": "https://api.github.com/users/aandukuria", "html_url": "https://github.com/aandukuria", "followers_url": "https://api.github.com/users/aandukuria/followers", "following_url": "https://api.github.com/users/aandukuria/following{/other_user}", "gists_url": "https://api.github.com/users/aandukuria/gists{/gist_id}", "starred_url": "https://api.github.com/users/aandukuria/starred{/owner}{/repo}", "subscriptions_url": "https://api.github.com/users/aandukuria/subscriptions", "organizations_url": "https://api.github.com/users/aandukuria/orgs", "repos_url": "https://api.github.com/users/aandukuria/repos", "events_url": "https://api.github.com/users/aandukuria/events{/privacy}", "received_events_url": "https://api.github.com/users/aandukuria/received_events", "type": "User", "user_view_type": "public", "site_admin": false}, {"login": "AArnott", "id": 3548, "node_id": "MDQ6VXNlcjM1NDg=", "avatar_url": "https://avatars.githubusercontent.com/u/3548?v=4", "gravatar_id": "", "url": "https://api.github.com/users/AArnott", "html_url": "https://github.com/AArnott", "followers_url": "https://api.github.com/users/AArnott/followers", "following_url": "https://api.github.com/users/AArnott/following{/other_user}", "gists_url": "https://api.github.com/users/AArnott/gists{/gist_id}", "starred_url": "https://api.github.com/users/AArnott/starred{/owner}{/repo}", "subscriptions_url": "https://api.github.com/users/AArnott/subscriptions", "organizations_url": "https://api.github.com/users/AArnott/orgs", "repos_url": "https://api.github.com/users/AArnott/repos", "events_url": "https://api.github.com/users/AArnott/events{/privacy}", "received_events_url": "https://api.github.com/users/AArnott/received_events", "type": "User", "user_view_type": "public", "site_admin": true}, {"login": "aaronborjas", "id": 40244238, "node_id": "MDQ6VXNlcjQwMjQ0MjM4", "avatar_url": "https://avatars.githubusercontent.com/u/40244238?v=4", "gravatar_id": "", "url": "https://api.github.com/users/aaronborjas", "html_url": "https://github.com/aaronborjas", "followers_url": "https://api.github.com/users/aaronborjas/followers", "following_url": "https://api.github.com/users/aaronborjas/following{/other_user}", "gists_url": "https://api.github.com/users/aaronborjas/gists{/gist_id}", "starred_url": "https://api.github.com/users/aaronborjas/starred{/owner}{/repo}", "subscriptions_url": "https://api.github.com/users/aaronborjas/subscriptions", "organizations_url": "https://api.github.com/users/aaronborjas/orgs", "repos_url": "https://api.github.com/users/aaronborjas/repos", "events_url": "https://api.github.com/users/aaronborjas/events{/privacy}", "received_events_url": "https://api.github.com/users/aaronborjas/received_events", "type": "User", "user_view_type": "public", "site_admin": false}, {"login": "aarongustafson", "id": 75736, "node_id": "MDQ6VXNlcjc1NzM2", "avatar_url": "https://avatars.githubusercontent.com/u/75736?v=4", "gravatar_id": "", "url": "https://api.github.com/users/aarongustafson", "html_url": "https://github.com/aarongustafson", "followers_url": "https://api.github.com/users/aarongustafson/followers", "following_url": "https://api.github.com/users/aarongustafson/following{/other_user}", "gists_url": "https://api.github.com/users/aarongustafson/gists{/gist_id}", "starred_url": "https://api.github.com/users/aarongustafson/starred{/owner}{/repo}", "subscriptions_url": "https://api.github.com/users/aarongustafson/subscriptions", "organizations_url": "https://api.github.com/users/aarongustafson/orgs", "repos_url": "https://api.github.com/users/aarongustafson/repos", "events_url": "https://api.github.com/users/aarongustafson/events{/privacy}", "received_events_url": "https://api.github.com/users/aarongustafson/received_events", "type": "User", "user_view_type": "public", "site_admin": false}, {"login": "AaronRM", "id": 437496, "node_id": "MDQ6VXNlcjQzNzQ5Ng==", "avatar_url": "https://avatars.githubusercontent.com/u/437496?v=4", "gravatar_id": "", "url": "https://api.github.com/users/AaronRM", "html_url": "https://github.com/AaronRM", "followers_url": "https://api.github.com/users/AaronRM/followers", "following_url": "https://api.github.com/users/AaronRM/following{/other_user}", "gists_url": "https://api.github.com/users/AaronRM/gists{/gist_id}", "starred_url": "https://api.github.com/users/AaronRM/starred{/owner}{/repo}", "subscriptions_url": "https://api.github.com/users/AaronRM/subscriptions", "organizations_url": "https://api.github.com/users/AaronRM/orgs", "repos_url": "https://api.github.com/users/AaronRM/repos", "events_url": "https://api.github.com/users/AaronRM/events{/privacy}", "received_events_url": "https://api.github.com/users/AaronRM/received_events", "type": "User", "user_view_type": "public", "site_admin": false}, {"login": "AaronRobinsonMSFT", "id": 30635565, "node_id": "MDQ6VXNlcjMwNjM1NTY1", "avatar_url": "https://avatars.githubusercontent.com/u/30635565?v=4", "gravatar_id": "", "url": "https://api.github.com/users/AaronRobinsonMSFT", "html_url": "https://github.com/AaronRobinsonMSFT", "followers_url": "https://api.github.com/users/AaronRobinsonMSFT/followers", "following_url": "https://api.github.com/users/AaronRobinsonMSFT/following{/other_user}", "gists_url": "https://api.github.com/users/AaronRobinsonMSFT/gists{/gist_id}", "starred_url": "https://api.github.com/users/AaronRobinsonMSFT/starred{/owner}{/repo}", "subscriptions_url": "https://api.github.com/users/AaronRobinsonMSFT/subscriptions", "organizations_url": "https://api.github.com/users/AaronRobinsonMSFT/orgs", "repos_url": "https://api.github.com/users/AaronRobinsonMSFT/repos", "events_url": "https://api.github.com/users/AaronRobinsonMSFT/events{/privacy}", "received_events_url": "https://api.github.com/users/AaronRobinsonMSFT/received_events", "type": "User", "user_view_type": "public", "site_admin": false}, {"login": "aasim", "id": 169527, "node_id": "MDQ6VXNlcjE2OTUyNw==", "avatar_url": "https://avatars.githubusercontent.com/u/169527?v=4", "gravatar_id": "", "url": "https://api.github.com/users/aasim", "html_url": "https://github.com/aasim", "followers_url": "https://api.github.com/users/aasim/followers", "following_url": "https://api.github.com/users/aasim/following{/other_user}", "gists_url": "https://api.github.com/users/aasim/gists{/gist_id}", "starred_url": "https://api.github.com/users/aasim/starred{/owner}{/repo}", "subscriptions_url": "https://api.github.com/users/aasim/subscriptions", "organizations_url": "https://api.github.com/users/aasim/orgs", "repos_url": "https://api.github.com/users/aasim/repos", "events_url": "https://api.github.com/users/aasim/events{/privacy}", "received_events_url": "https://api.github.com/users/aasim/received_events", "type": "User", "user_view_type": "public", "site_admin": false}, {"login": "aavalang", "id": 56377848, "node_id": "MDQ6VXNlcjU2Mzc3ODQ4", "avatar_url": "https://avatars.githubusercontent.com/u/56377848?v=4", "gravatar_id": "", "url": "https://api.github.com/users/aavalang", "html_url": "https://github.com/aavalang", "followers_url": "https://api.github.com/users/aavalang/followers", "following_url": "https://api.github.com/users/aavalang/following{/other_user}", "gists_url": "https://api.github.com/users/aavalang/gists{/gist_id}", "starred_url": "https://api.github.com/users/aavalang/starred{/owner}{/repo}", "subscriptions_url": "https://api.github.com/users/aavalang/subscriptions", "organizations_url": "https://api.github.com/users/aavalang/orgs", "repos_url": "https://api.github.com/users/aavalang/repos", "events_url": "https://api.github.com/users/aavalang/events{/privacy}", "received_events_url": "https://api.github.com/users/aavalang/received_events", "type": "User", "user_view_type": "public", "site_admin": false}, {"login": "abbyjshen", "id": 40477007, "node_id": "MDQ6VXNlcjQwNDc3MDA3", "avatar_url": "https://avatars.githubusercontent.com/u/40477007?v=4", "gravatar_id": "", "url": "https://api.github.com/users/abbyjshen", "html_url": "https://github.com/abbyjshen", "followers_url": "https://api.github.com/users/abbyjshen/followers", "following_url": "https://api.github.com/users/abbyjshen/following{/other_user}", "gists_url": "https://api.github.com/users/abbyjshen/gists{/gist_id}", "starred_url": "https://api.github.com/users/abbyjshen/starred{/owner}{/repo}", "subscriptions_url": "https://api.github.com/users/abbyjshen/subscriptions", "organizations_url": "https://api.github.com/users/abbyjshen/orgs", "repos_url": "https://api.github.com/users/abbyjshen/repos", "events_url": "https://api.github.com/users/abbyjshen/events{/privacy}", "received_events_url": "https://api.github.com/users/abbyjshen/received_events", "type": "User", "user_view_type": "public", "site_admin": false}, {"login": "abbyzahne", "id": 33647063, "node_id": "MDQ6VXNlcjMzNjQ3MDYz", "avatar_url": "https://avatars.githubusercontent.com/u/33647063?v=4", "gravatar_id": "", "url": "https://api.github.com/users/abbyzahne", "html_url": "https://github.com/abbyzahne", "followers_url": "https://api.github.com/users/abbyzahne/followers", "following_url": "https://api.github.com/users/abbyzahne/following{/other_user}", "gists_url": "https://api.github.com/users/abbyzahne/gists{/gist_id}", "starred_url": "https://api.github.com/users/abbyzahne/starred{/owner}{/repo}", "subscriptions_url": "https://api.github.com/users/abbyzahne/subscriptions", "organizations_url": "https://api.github.com/users/abbyzahne/orgs", "repos_url": "https://api.github.com/users/abbyzahne/repos", "events_url": "https://api.github.com/users/abbyzahne/events{/privacy}", "received_events_url": "https://api.github.com/users/abbyzahne/received_events", "type": "User", "user_view_type": "public", "site_admin": false}, {"login": "abeckDev", "id": 8720854, "node_id": "MDQ6VXNlcjg3MjA4NTQ=", "avatar_url": "https://avatars.githubusercontent.com/u/8720854?v=4", "gravatar_id": "", "url": "https://api.github.com/users/abeckDev", "html_url": "https://github.com/abeckDev", "followers_url": "https://api.github.com/users/abeckDev/followers", "following_url": "https://api.github.com/users/abeckDev/following{/other_user}", "gists_url": "https://api.github.com/users/abeckDev/gists{/gist_id}", "starred_url": "https://api.github.com/users/abeckDev/starred{/owner}{/repo}", "subscriptions_url": "https://api.github.com/users/abeckDev/subscriptions", "organizations_url": "https://api.github.com/users/abeckDev/orgs", "repos_url": "https://api.github.com/users/abeckDev/repos", "events_url": "https://api.github.com/users/abeckDev/events{/privacy}", "received_events_url": "https://api.github.com/users/abeckDev/received_events", "type": "User", "user_view_type": "public", "site_admin": false}, {"login": "abgoswam", "id": 8822956, "node_id": "MDQ6VXNlcjg4MjI5NTY=", "avatar_url": "https://avatars.githubusercontent.com/u/8822956?v=4", "gravatar_id": "", "url": "https://api.github.com/users/abgoswam", "html_url": "https://github.com/abgoswam", "followers_url": "https://api.github.com/users/abgoswam/followers", "following_url": "https://api.github.com/users/abgoswam/following{/other_user}", "gists_url": "https://api.github.com/users/abgoswam/gists{/gist_id}", "starred_url": "https://api.github.com/users/abgoswam/starred{/owner}{/repo}", "subscriptions_url": "https://api.github.com/users/abgoswam/subscriptions", "organizations_url": "https://api.github.com/users/abgoswam/orgs", "repos_url": "https://api.github.com/users/abgoswam/repos", "events_url": "https://api.github.com/users/abgoswam/events{/privacy}", "received_events_url": "https://api.github.com/users/abgoswam/received_events", "type": "User", "user_view_type": "public", "site_admin": true}, {"login": "abhayohri", "id": 111389143, "node_id": "U_kgDOBqOp1w", "avatar_url": "https://avatars.githubusercontent.com/u/111389143?v=4", "gravatar_id": "", "url": "https://api.github.com/users/abhayohri", "html_url": "https://github.com/abhayohri", "followers_url": "https://api.github.com/users/abhayohri/followers", "following_url": "https://api.github.com/users/abhayohri/following{/other_user}", "gists_url": "https://api.github.com/users/abhayohri/gists{/gist_id}", "starred_url": "https://api.github.com/users/abhayohri/starred{/owner}{/repo}", "subscriptions_url": "https://api.github.com/users/abhayohri/subscriptions", "organizations_url": "https://api.github.com/users/abhayohri/orgs", "repos_url": "https://api.github.com/users/abhayohri/repos", "events_url": "https://api.github.com/users/abhayohri/events{/privacy}", "received_events_url": "https://api.github.com/users/abhayohri/received_events", "type": "User", "user_view_type": "public", "site_admin": false}, {"login": "abhijdas", "id": 177531127, "node_id": "U_kgDOCpTo9w", "avatar_url": "https://avatars.githubusercontent.com/u/177531127?v=4", "gravatar_id": "", "url": "https://api.github.com/users/abhijdas", "html_url": "https://github.com/abhijdas", "followers_url": "https://api.github.com/users/abhijdas/followers", "following_url": "https://api.github.com/users/abhijdas/following{/other_user}", "gists_url": "https://api.github.com/users/abhijdas/gists{/gist_id}", "starred_url": "https://api.github.com/users/abhijdas/starred{/owner}{/repo}", "subscriptions_url": "https://api.github.com/users/abhijdas/subscriptions", "organizations_url": "https://api.github.com/users/abhijdas/orgs", "repos_url": "https://api.github.com/users/abhijdas/repos", "events_url": "https://api.github.com/users/abhijdas/events{/privacy}", "received_events_url": "https://api.github.com/users/abhijdas/received_events", "type": "User", "user_view_type": "public", "site_admin": false}, {"login": "abhinav-ghai", "id": 1511158, "node_id": "MDQ6VXNlcjE1MTExNTg=", "avatar_url": "https://avatars.githubusercontent.com/u/1511158?v=4", "gravatar_id": "", "url": "https://api.github.com/users/abhinav-ghai", "html_url": "https://github.com/abhinav-ghai", "followers_url": "https://api.github.com/users/abhinav-ghai/followers", "following_url": "https://api.github.com/users/abhinav-ghai/following{/other_user}", "gists_url": "https://api.github.com/users/abhinav-ghai/gists{/gist_id}", "starred_url": "https://api.github.com/users/abhinav-ghai/starred{/owner}{/repo}", "subscriptions_url": "https://api.github.com/users/abhinav-ghai/subscriptions", "organizations_url": "https://api.github.com/users/abhinav-ghai/orgs", "repos_url": "https://api.github.com/users/abhinav-ghai/repos", "events_url": "https://api.github.com/users/abhinav-ghai/events{/privacy}", "received_events_url": "https://api.github.com/users/abhinav-ghai/received_events", "type": "User", "user_view_type": "public", "site_admin": false}, {"login": "AbhinavSinghT", "id": 18618283, "node_id": "MDQ6VXNlcjE4NjE4Mjgz", "avatar_url": "https://avatars.githubusercontent.com/u/18618283?v=4", "gravatar_id": "", "url": "https://api.github.com/users/AbhinavSinghT", "html_url": "https://github.com/AbhinavSinghT", "followers_url": "https://api.github.com/users/AbhinavSinghT/followers", "following_url": "https://api.github.com/users/AbhinavSinghT/following{/other_user}", "gists_url": "https://api.github.com/users/AbhinavSinghT/gists{/gist_id}", "starred_url": "https://api.github.com/users/AbhinavSinghT/starred{/owner}{/repo}", "subscriptions_url": "https://api.github.com/users/AbhinavSinghT/subscriptions", "organizations_url": "https://api.github.com/users/AbhinavSinghT/orgs", "repos_url": "https://api.github.com/users/AbhinavSinghT/repos", "events_url": "https://api.github.com/users/AbhinavSinghT/events{/privacy}", "received_events_url": "https://api.github.com/users/AbhinavSinghT/received_events", "type": "User", "user_view_type": "public", "site_admin": false}, {"login": "abhinitkumar01", "id": 89906029, "node_id": "MDQ6VXNlcjg5OTA2MDI5", "avatar_url": "https://avatars.githubusercontent.com/u/89906029?v=4", "gravatar_id": "", "url": "https://api.github.com/users/abhinitkumar01", "html_url": "https://github.com/abhinitkumar01", "followers_url": "https://api.github.com/users/abhinitkumar01/followers", "following_url": "https://api.github.com/users/abhinitkumar01/following{/other_user}", "gists_url": "https://api.github.com/users/abhinitkumar01/gists{/gist_id}", "starred_url": "https://api.github.com/users/abhinitkumar01/starred{/owner}{/repo}", "subscriptions_url": "https://api.github.com/users/abhinitkumar01/subscriptions", "organizations_url": "https://api.github.com/users/abhinitkumar01/orgs", "repos_url": "https://api.github.com/users/abhinitkumar01/repos", "events_url": "https://api.github.com/users/abhinitkumar01/events{/privacy}", "received_events_url": "https://api.github.com/users/abhinitkumar01/received_events", "type": "User", "user_view_type": "public", "site_admin": false}, {"login": "abhishea", "id": 13745286, "node_id": "MDQ6VXNlcjEzNzQ1Mjg2", "avatar_url": "https://avatars.githubusercontent.com/u/13745286?v=4", "gravatar_id": "", "url": "https://api.github.com/users/abhishea", "html_url": "https://github.com/abhishea", "followers_url": "https://api.github.com/users/abhishea/followers", "following_url": "https://api.github.com/users/abhishea/following{/other_user}", "gists_url": "https://api.github.com/users/abhishea/gists{/gist_id}", "starred_url": "https://api.github.com/users/abhishea/starred{/owner}{/repo}", "subscriptions_url": "https://api.github.com/users/abhishea/subscriptions", "organizations_url": "https://api.github.com/users/abhishea/orgs", "repos_url": "https://api.github.com/users/abhishea/repos", "events_url": "https://api.github.com/users/abhishea/events{/privacy}", "received_events_url": "https://api.github.com/users/abhishea/received_events", "type": "User", "user_view_type": "public", "site_admin": false}, {"login": "abhishek-corp", "id": 104534488, "node_id": "U_kgDOBjsR2A", "avatar_url": "https://avatars.githubusercontent.com/u/104534488?v=4", "gravatar_id": "", "url": "https://api.github.com/users/abhishek-corp", "html_url": "https://github.com/abhishek-corp", "followers_url": "https://api.github.com/users/abhishek-corp/followers", "following_url": "https://api.github.com/users/abhishek-corp/following{/other_user}", "gists_url": "https://api.github.com/users/abhishek-corp/gists{/gist_id}", "starred_url": "https://api.github.com/users/abhishek-corp/starred{/owner}{/repo}", "subscriptions_url": "https://api.github.com/users/abhishek-corp/subscriptions", "organizations_url": "https://api.github.com/users/abhishek-corp/orgs", "repos_url": "https://api.github.com/users/abhishek-corp/repos", "events_url": "https://api.github.com/users/abhishek-corp/events{/privacy}", "received_events_url": "https://api.github.com/users/abhishek-corp/received_events", "type": "User", "user_view_type": "public", "site_admin": false}, {"login": "abhishek-pandey-1", "id": 82105651, "node_id": "MDQ6VXNlcjgyMTA1NjUx", "avatar_url": "https://avatars.githubusercontent.com/u/82105651?v=4", "gravatar_id": "", "url": "https://api.github.com/users/abhishek-pandey-1", "html_url": "https://github.com/abhishek-pandey-1", "followers_url": "https://api.github.com/users/abhishek-pandey-1/followers", "following_url": "https://api.github.com/users/abhishek-pandey-1/following{/other_user}", "gists_url": "https://api.github.com/users/abhishek-pandey-1/gists{/gist_id}", "starred_url": "https://api.github.com/users/abhishek-pandey-1/starred{/owner}{/repo}", "subscriptions_url": "https://api.github.com/users/abhishek-pandey-1/subscriptions", "organizations_url": "https://api.github.com/users/abhishek-pandey-1/orgs", "repos_url": "https://api.github.com/users/abhishek-pandey-1/repos", "events_url": "https://api.github.com/users/abhishek-pandey-1/events{/privacy}", "received_events_url": "https://api.github.com/users/abhishek-pandey-1/received_events", "type": "User", "user_view_type": "public", "site_admin": false}, {"login": "abhishek-shanthkumar", "id": 9668693, "node_id": "MDQ6VXNlcjk2Njg2OTM=", "avatar_url": "https://avatars.githubusercontent.com/u/9668693?v=4", "gravatar_id": "", "url": "https://api.github.com/users/abhishek-shanthkumar", "html_url": "https://github.com/abhishek-shanthkumar", "followers_url": "https://api.github.com/users/abhishek-shanthkumar/followers", "following_url": "https://api.github.com/users/abhishek-shanthkumar/following{/other_user}", "gists_url": "https://api.github.com/users/abhishek-shanthkumar/gists{/gist_id}", "starred_url": "https://api.github.com/users/abhishek-shanthkumar/starred{/owner}{/repo}", "subscriptions_url": "https://api.github.com/users/abhishek-shanthkumar/subscriptions", "organizations_url": "https://api.github.com/users/abhishek-shanthkumar/orgs", "repos_url": "https://api.github.com/users/abhishek-shanthkumar/repos", "events_url": "https://api.github.com/users/abhishek-shanthkumar/events{/privacy}", "received_events_url": "https://api.github.com/users/abhishek-shanthkumar/received_events", "type": "User", "user_view_type": "public", "site_admin": false}, {"login": "abhiskuma77", "id": 171618318, "node_id": "U_kgDOCjqwDg", "avatar_url": "https://avatars.githubusercontent.com/u/171618318?v=4", "gravatar_id": "", "url": "https://api.github.com/users/abhiskuma77", "html_url": "https://github.com/abhiskuma77", "followers_url": "https://api.github.com/users/abhiskuma77/followers", "following_url": "https://api.github.com/users/abhiskuma77/following{/other_user}", "gists_url": "https://api.github.com/users/abhiskuma77/gists{/gist_id}", "starred_url": "https://api.github.com/users/abhiskuma77/starred{/owner}{/repo}", "subscriptions_url": "https://api.github.com/users/abhiskuma77/subscriptions", "organizations_url": "https://api.github.com/users/abhiskuma77/orgs", "repos_url": "https://api.github.com/users/abhiskuma77/repos", "events_url": "https://api.github.com/users/abhiskuma77/events{/privacy}", "received_events_url": "https://api.github.com/users/abhiskuma77/received_events", "type": "User", "user_view_type": "public", "site_admin": false}, {"login": "abranj19", "id": 134475350, "node_id": "U_kgDOCAPuVg", "avatar_url": "https://avatars.githubusercontent.com/u/134475350?v=4", "gravatar_id": "", "url": "https://api.github.com/users/abranj19", "html_url": "https://github.com/abranj19", "followers_url": "https://api.github.com/users/abranj19/followers", "following_url": "https://api.github.com/users/abranj19/following{/other_user}", "gists_url": "https://api.github.com/users/abranj19/gists{/gist_id}", "starred_url": "https://api.github.com/users/abranj19/starred{/owner}{/repo}", "subscriptions_url": "https://api.github.com/users/abranj19/subscriptions", "organizations_url": "https://api.github.com/users/abranj19/orgs", "repos_url": "https://api.github.com/users/abranj19/repos", "events_url": "https://api.github.com/users/abranj19/events{/privacy}", "received_events_url": "https://api.github.com/users/abranj19/received_events", "type": "User", "user_view_type": "public", "site_admin": true}, {"login": "abster95", "id": 17542319, "node_id": "MDQ6VXNlcjE3NTQyMzE5", "avatar_url": "https://avatars.githubusercontent.com/u/17542319?v=4", "gravatar_id": "", "url": "https://api.github.com/users/abster95", "html_url": "https://github.com/abster95", "followers_url": "https://api.github.com/users/abster95/followers", "following_url": "https://api.github.com/users/abster95/following{/other_user}", "gists_url": "https://api.github.com/users/abster95/gists{/gist_id}", "starred_url": "https://api.github.com/users/abster95/starred{/owner}{/repo}", "subscriptions_url": "https://api.github.com/users/abster95/subscriptions", "organizations_url": "https://api.github.com/users/abster95/orgs", "repos_url": "https://api.github.com/users/abster95/repos", "events_url": "https://api.github.com/users/abster95/events{/privacy}", "received_events_url": "https://api.github.com/users/abster95/received_events", "type": "User", "user_view_type": "public", "site_admin": false}, {"login": "abuccts", "id": 13360214, "node_id": "MDQ6VXNlcjEzMzYwMjE0", "avatar_url": "https://avatars.githubusercontent.com/u/13360214?v=4", "gravatar_id": "", "url": "https://api.github.com/users/abuccts", "html_url": "https://github.com/abuccts", "followers_url": "https://api.github.com/users/abuccts/followers", "following_url": "https://api.github.com/users/abuccts/following{/other_user}", "gists_url": "https://api.github.com/users/abuccts/gists{/gist_id}", "starred_url": "https://api.github.com/users/abuccts/starred{/owner}{/repo}", "subscriptions_url": "https://api.github.com/users/abuccts/subscriptions", "organizations_url": "https://api.github.com/users/abuccts/orgs", "repos_url": "https://api.github.com/users/abuccts/repos", "events_url": "https://api.github.com/users/abuccts/events{/privacy}", "received_events_url": "https://api.github.com/users/abuccts/received_events", "type": "User", "user_view_type": "public", "site_admin": false}, {"login": "acangialosi", "id": 5457010, "node_id": "MDQ6VXNlcjU0NTcwMTA=", "avatar_url": "https://avatars.githubusercontent.com/u/5457010?v=4", "gravatar_id": "", "url": "https://api.github.com/users/acangialosi", "html_url": "https://github.com/acangialosi", "followers_url": "https://api.github.com/users/acangialosi/followers", "following_url": "https://api.github.com/users/acangialosi/following{/other_user}", "gists_url": "https://api.github.com/users/acangialosi/gists{/gist_id}", "starred_url": "https://api.github.com/users/acangialosi/starred{/owner}{/repo}", "subscriptions_url": "https://api.github.com/users/acangialosi/subscriptions", "organizations_url": "https://api.github.com/users/acangialosi/orgs", "repos_url": "https://api.github.com/users/acangialosi/repos", "events_url": "https://api.github.com/users/acangialosi/events{/privacy}", "received_events_url": "https://api.github.com/users/acangialosi/received_events", "type": "User", "user_view_type": "public", "site_admin": false}, {"login": "achamayou", "id": 4016369, "node_id": "MDQ6VXNlcjQwMTYzNjk=", "avatar_url": "https://avatars.githubusercontent.com/u/4016369?v=4", "gravatar_id": "", "url": "https://api.github.com/users/achamayou", "html_url": "https://github.com/achamayou", "followers_url": "https://api.github.com/users/achamayou/followers", "following_url": "https://api.github.com/users/achamayou/following{/other_user}", "gists_url": "https://api.github.com/users/achamayou/gists{/gist_id}", "starred_url": "https://api.github.com/users/achamayou/starred{/owner}{/repo}", "subscriptions_url": "https://api.github.com/users/achamayou/subscriptions", "organizations_url": "https://api.github.com/users/achamayou/orgs", "repos_url": "https://api.github.com/users/achamayou/repos", "events_url": "https://api.github.com/users/achamayou/events{/privacy}", "received_events_url": "https://api.github.com/users/achamayou/received_events", "type": "User", "user_view_type": "public", "site_admin": false}, {"login": "achauhan-scc", "id": 70937115, "node_id": "MDQ6VXNlcjcwOTM3MTE1", "avatar_url": "https://avatars.githubusercontent.com/u/70937115?v=4", "gravatar_id": "", "url": "https://api.github.com/users/achauhan-scc", "html_url": "https://github.com/achauhan-scc", "followers_url": "https://api.github.com/users/achauhan-scc/followers", "following_url": "https://api.github.com/users/achauhan-scc/following{/other_user}", "gists_url": "https://api.github.com/users/achauhan-scc/gists{/gist_id}", "starred_url": "https://api.github.com/users/achauhan-scc/starred{/owner}{/repo}", "subscriptions_url": "https://api.github.com/users/achauhan-scc/subscriptions", "organizations_url": "https://api.github.com/users/achauhan-scc/orgs", "repos_url": "https://api.github.com/users/achauhan-scc/repos", "events_url": "https://api.github.com/users/achauhan-scc/events{/privacy}", "received_events_url": "https://api.github.com/users/achauhan-scc/received_events", "type": "User", "user_view_type": "public", "site_admin": false}, {"login": "AchoArnold", "id": 4196457, "node_id": "MDQ6VXNlcjQxOTY0NTc=", "avatar_url": "https://avatars.githubusercontent.com/u/4196457?v=4", "gravatar_id": "", "url": "https://api.github.com/users/AchoArnold", "html_url": "https://github.com/AchoArnold", "followers_url": "https://api.github.com/users/AchoArnold/followers", "following_url": "https://api.github.com/users/AchoArnold/following{/other_user}", "gists_url": "https://api.github.com/users/AchoArnold/gists{/gist_id}", "starred_url": "https://api.github.com/users/AchoArnold/starred{/owner}{/repo}", "subscriptions_url": "https://api.github.com/users/AchoArnold/subscriptions", "organizations_url": "https://api.github.com/users/AchoArnold/orgs", "repos_url": "https://api.github.com/users/AchoArnold/repos", "events_url": "https://api.github.com/users/AchoArnold/events{/privacy}", "received_events_url": "https://api.github.com/users/AchoArnold/received_events", "type": "User", "user_view_type": "public", "site_admin": false}, {"login": "achyuth-ms", "id": 66455292, "node_id": "MDQ6VXNlcjY2NDU1Mjky", "avatar_url": "https://avatars.githubusercontent.com/u/66455292?v=4", "gravatar_id": "", "url": "https://api.github.com/users/achyuth-ms", "html_url": "https://github.com/achyuth-ms", "followers_url": "https://api.github.com/users/achyuth-ms/followers", "following_url": "https://api.github.com/users/achyuth-ms/following{/other_user}", "gists_url": "https://api.github.com/users/achyuth-ms/gists{/gist_id}", "starred_url": "https://api.github.com/users/achyuth-ms/starred{/owner}{/repo}", "subscriptions_url": "https://api.github.com/users/achyuth-ms/subscriptions", "organizations_url": "https://api.github.com/users/achyuth-ms/orgs", "repos_url": "https://api.github.com/users/achyuth-ms/repos", "events_url": "https://api.github.com/users/achyuth-ms/events{/privacy}", "received_events_url": "https://api.github.com/users/achyuth-ms/received_events", "type": "User", "user_view_type": "public", "site_admin": false}, {"login": "aconsuegra", "id": 1814882, "node_id": "MDQ6VXNlcjE4MTQ4ODI=", "avatar_url": "https://avatars.githubusercontent.com/u/1814882?v=4", "gravatar_id": "", "url": "https://api.github.com/users/aconsuegra", "html_url": "https://github.com/aconsuegra", "followers_url": "https://api.github.com/users/aconsuegra/followers", "following_url": "https://api.github.com/users/aconsuegra/following{/other_user}", "gists_url": "https://api.github.com/users/aconsuegra/gists{/gist_id}", "starred_url": "https://api.github.com/users/aconsuegra/starred{/owner}{/repo}", "subscriptions_url": "https://api.github.com/users/aconsuegra/subscriptions", "organizations_url": "https://api.github.com/users/aconsuegra/orgs", "repos_url": "https://api.github.com/users/aconsuegra/repos", "events_url": "https://api.github.com/users/aconsuegra/events{/privacy}", "received_events_url": "https://api.github.com/users/aconsuegra/received_events", "type": "User", "user_view_type": "public", "site_admin": true}, {"login": "acortelyou", "id": 1689668, "node_id": "MDQ6VXNlcjE2ODk2Njg=", "avatar_url": "https://avatars.githubusercontent.com/u/1689668?v=4", "gravatar_id": "", "url": "https://api.github.com/users/acortelyou", "html_url": "https://github.com/acortelyou", "followers_url": "https://api.github.com/users/acortelyou/followers", "following_url": "https://api.github.com/users/acortelyou/following{/other_user}", "gists_url": "https://api.github.com/users/acortelyou/gists{/gist_id}", "starred_url": "https://api.github.com/users/acortelyou/starred{/owner}{/repo}", "subscriptions_url": "https://api.github.com/users/acortelyou/subscriptions", "organizations_url": "https://api.github.com/users/acortelyou/orgs", "repos_url": "https://api.github.com/users/acortelyou/repos", "events_url": "https://api.github.com/users/acortelyou/events{/privacy}", "received_events_url": "https://api.github.com/users/acortelyou/received_events", "type": "User", "user_view_type": "public", "site_admin": false}, {"login": "acrown-msft", "id": 17282295, "node_id": "MDQ6VXNlcjE3MjgyMjk1", "avatar_url": "https://avatars.githubusercontent.com/u/17282295?v=4", "gravatar_id": "", "url": "https://api.github.com/users/acrown-msft", "html_url": "https://github.com/acrown-msft", "followers_url": "https://api.github.com/users/acrown-msft/followers", "following_url": "https://api.github.com/users/acrown-msft/following{/other_user}", "gists_url": "https://api.github.com/users/acrown-msft/gists{/gist_id}", "starred_url": "https://api.github.com/users/acrown-msft/starred{/owner}{/repo}", "subscriptions_url": "https://api.github.com/users/acrown-msft/subscriptions", "organizations_url": "https://api.github.com/users/acrown-msft/orgs", "repos_url": "https://api.github.com/users/acrown-msft/repos", "events_url": "https://api.github.com/users/acrown-msft/events{/privacy}", "received_events_url": "https://api.github.com/users/acrown-msft/received_events", "type": "User", "user_view_type": "public", "site_admin": false}, {"login": "adaggarwal", "id": 22264147, "node_id": "MDQ6VXNlcjIyMjY0MTQ3", "avatar_url": "https://avatars.githubusercontent.com/u/22264147?v=4", "gravatar_id": "", "url": "https://api.github.com/users/adaggarwal", "html_url": "https://github.com/adaggarwal", "followers_url": "https://api.github.com/users/adaggarwal/followers", "following_url": "https://api.github.com/users/adaggarwal/following{/other_user}", "gists_url": "https://api.github.com/users/adaggarwal/gists{/gist_id}", "starred_url": "https://api.github.com/users/adaggarwal/starred{/owner}{/repo}", "subscriptions_url": "https://api.github.com/users/adaggarwal/subscriptions", "organizations_url": "https://api.github.com/users/adaggarwal/orgs", "repos_url": "https://api.github.com/users/adaggarwal/repos", "events_url": "https://api.github.com/users/adaggarwal/events{/privacy}", "received_events_url": "https://api.github.com/users/adaggarwal/received_events", "type": "User", "user_view_type": "public", "site_admin": false}, {"login": "adamasmar", "id": 35544437, "node_id": "MDQ6VXNlcjM1NTQ0NDM3", "avatar_url": "https://avatars.githubusercontent.com/u/35544437?v=4", "gravatar_id": "", "url": "https://api.github.com/users/adamasmar", "html_url": "https://github.com/adamasmar", "followers_url": "https://api.github.com/users/adamasmar/followers", "following_url": "https://api.github.com/users/adamasmar/following{/other_user}", "gists_url": "https://api.github.com/users/adamasmar/gists{/gist_id}", "starred_url": "https://api.github.com/users/adamasmar/starred{/owner}{/repo}", "subscriptions_url": "https://api.github.com/users/adamasmar/subscriptions", "organizations_url": "https://api.github.com/users/adamasmar/orgs", "repos_url": "https://api.github.com/users/adamasmar/repos", "events_url": "https://api.github.com/users/adamasmar/events{/privacy}", "received_events_url": "https://api.github.com/users/adamasmar/received_events", "type": "User", "user_view_type": "public", "site_admin": false}, {"login": "adamgitazure", "id": 70923794, "node_id": "MDQ6VXNlcjcwOTIzNzk0", "avatar_url": "https://avatars.githubusercontent.com/u/70923794?v=4", "gravatar_id": "", "url": "https://api.github.com/users/adamgitazure", "html_url": "https://github.com/adamgitazure", "followers_url": "https://api.github.com/users/adamgitazure/followers", "following_url": "https://api.github.com/users/adamgitazure/following{/other_user}", "gists_url": "https://api.github.com/users/adamgitazure/gists{/gist_id}", "starred_url": "https://api.github.com/users/adamgitazure/starred{/owner}{/repo}", "subscriptions_url": "https://api.github.com/users/adamgitazure/subscriptions", "organizations_url": "https://api.github.com/users/adamgitazure/orgs", "repos_url": "https://api.github.com/users/adamgitazure/repos", "events_url": "https://api.github.com/users/adamgitazure/events{/privacy}", "received_events_url": "https://api.github.com/users/adamgitazure/received_events", "type": "User", "user_view_type": "public", "site_admin": false}, {"login": "adamint", "id": 20359921, "node_id": "MDQ6VXNlcjIwMzU5OTIx", "avatar_url": "https://avatars.githubusercontent.com/u/20359921?v=4", "gravatar_id": "", "url": "https://api.github.com/users/adamint", "html_url": "https://github.com/adamint", "followers_url": "https://api.github.com/users/adamint/followers", "following_url": "https://api.github.com/users/adamint/following{/other_user}", "gists_url": "https://api.github.com/users/adamint/gists{/gist_id}", "starred_url": "https://api.github.com/users/adamint/starred{/owner}{/repo}", "subscriptions_url": "https://api.github.com/users/adamint/subscriptions", "organizations_url": "https://api.github.com/users/adamint/orgs", "repos_url": "https://api.github.com/users/adamint/repos", "events_url": "https://api.github.com/users/adamint/events{/privacy}", "received_events_url": "https://api.github.com/users/adamint/received_events", "type": "User", "user_view_type": "public", "site_admin": false}, {"login": "adamjbrewer", "id": 65310631, "node_id": "MDQ6VXNlcjY1MzEwNjMx", "avatar_url": "https://avatars.githubusercontent.com/u/65310631?v=4", "gravatar_id": "", "url": "https://api.github.com/users/adamjbrewer", "html_url": "https://github.com/adamjbrewer", "followers_url": "https://api.github.com/users/adamjbrewer/followers", "following_url": "https://api.github.com/users/adamjbrewer/following{/other_user}", "gists_url": "https://api.github.com/users/adamjbrewer/gists{/gist_id}", "starred_url": "https://api.github.com/users/adamjbrewer/starred{/owner}{/repo}", "subscriptions_url": "https://api.github.com/users/adamjbrewer/subscriptions", "organizations_url": "https://api.github.com/users/adamjbrewer/orgs", "repos_url": "https://api.github.com/users/adamjbrewer/repos", "events_url": "https://api.github.com/users/adamjbrewer/events{/privacy}", "received_events_url": "https://api.github.com/users/adamjbrewer/received_events", "type": "User", "user_view_type": "public", "site_admin": false}, {"login": "AdamJMiles", "id": 18439438, "node_id": "MDQ6VXNlcjE4NDM5NDM4", "avatar_url": "https://avatars.githubusercontent.com/u/18439438?v=4", "gravatar_id": "", "url": "https://api.github.com/users/AdamJMiles", "html_url": "https://github.com/AdamJMiles", "followers_url": "https://api.github.com/users/AdamJMiles/followers", "following_url": "https://api.github.com/users/AdamJMiles/following{/other_user}", "gists_url": "https://api.github.com/users/AdamJMiles/gists{/gist_id}", "starred_url": "https://api.github.com/users/AdamJMiles/starred{/owner}{/repo}", "subscriptions_url": "https://api.github.com/users/AdamJMiles/subscriptions", "organizations_url": "https://api.github.com/users/AdamJMiles/orgs", "repos_url": "https://api.github.com/users/AdamJMiles/repos", "events_url": "https://api.github.com/users/AdamJMiles/events{/privacy}", "received_events_url": "https://api.github.com/users/AdamJMiles/received_events", "type": "User", "user_view_type": "public", "site_admin": false}, {"login": "Adamkadaban", "id": 34610663, "node_id": "MDQ6VXNlcjM0NjEwNjYz", "avatar_url": "https://avatars.githubusercontent.com/u/34610663?v=4", "gravatar_id": "", "url": "https://api.github.com/users/Adamkadaban", "html_url": "https://github.com/Adamkadaban", "followers_url": "https://api.github.com/users/Adamkadaban/followers", "following_url": "https://api.github.com/users/Adamkadaban/following{/other_user}", "gists_url": "https://api.github.com/users/Adamkadaban/gists{/gist_id}", "starred_url": "https://api.github.com/users/Adamkadaban/starred{/owner}{/repo}", "subscriptions_url": "https://api.github.com/users/Adamkadaban/subscriptions", "organizations_url": "https://api.github.com/users/Adamkadaban/orgs", "repos_url": "https://api.github.com/users/Adamkadaban/repos", "events_url": "https://api.github.com/users/Adamkadaban/events{/privacy}", "received_events_url": "https://api.github.com/users/Adamkadaban/received_events", "type": "User", "user_view_type": "public", "site_admin": false}, {"login": "adamlash", "id": 68923704, "node_id": "MDQ6VXNlcjY4OTIzNzA0", "avatar_url": "https://avatars.githubusercontent.com/u/68923704?v=4", "gravatar_id": "", "url": "https://api.github.com/users/adamlash", "html_url": "https://github.com/adamlash", "followers_url": "https://api.github.com/users/adamlash/followers", "following_url": "https://api.github.com/users/adamlash/following{/other_user}", "gists_url": "https://api.github.com/users/adamlash/gists{/gist_id}", "starred_url": "https://api.github.com/users/adamlash/starred{/owner}{/repo}", "subscriptions_url": "https://api.github.com/users/adamlash/subscriptions", "organizations_url": "https://api.github.com/users/adamlash/orgs", "repos_url": "https://api.github.com/users/adamlash/repos", "events_url": "https://api.github.com/users/adamlash/events{/privacy}", "received_events_url": "https://api.github.com/users/adamlash/received_events", "type": "User", "user_view_type": "public", "site_admin": false}, {"login": "adamsitnik", "id": 6011991, "node_id": "MDQ6VXNlcjYwMTE5OTE=", "avatar_url": "https://avatars.githubusercontent.com/u/6011991?v=4", "gravatar_id": "", "url": "https://api.github.com/users/adamsitnik", "html_url": "https://github.com/adamsitnik", "followers_url": "https://api.github.com/users/adamsitnik/followers", "following_url": "https://api.github.com/users/adamsitnik/following{/other_user}", "gists_url": "https://api.github.com/users/adamsitnik/gists{/gist_id}", "starred_url": "https://api.github.com/users/adamsitnik/starred{/owner}{/repo}", "subscriptions_url": "https://api.github.com/users/adamsitnik/subscriptions", "organizations_url": "https://api.github.com/users/adamsitnik/orgs", "repos_url": "https://api.github.com/users/adamsitnik/repos", "events_url": "https://api.github.com/users/adamsitnik/events{/privacy}", "received_events_url": "https://api.github.com/users/adamsitnik/received_events", "type": "User", "user_view_type": "public", "site_admin": false}, {"login": "adamtuck-msft", "id": 97158274, "node_id": "U_kgDOBcqEgg", "avatar_url": "https://avatars.githubusercontent.com/u/97158274?v=4", "gravatar_id": "", "url": "https://api.github.com/users/adamtuck-msft", "html_url": "https://github.com/adamtuck-msft", "followers_url": "https://api.github.com/users/adamtuck-msft/followers", "following_url": "https://api.github.com/users/adamtuck-msft/following{/other_user}", "gists_url": "https://api.github.com/users/adamtuck-msft/gists{/gist_id}", "starred_url": "https://api.github.com/users/adamtuck-msft/starred{/owner}{/repo}", "subscriptions_url": "https://api.github.com/users/adamtuck-msft/subscriptions", "organizations_url": "https://api.github.com/users/adamtuck-msft/orgs", "repos_url": "https://api.github.com/users/adamtuck-msft/repos", "events_url": "https://api.github.com/users/adamtuck-msft/events{/privacy}", "received_events_url": "https://api.github.com/users/adamtuck-msft/received_events", "type": "User", "user_view_type": "public", "site_admin": false}, {"login": "adashen", "id": 1872137, "node_id": "MDQ6VXNlcjE4NzIxMzc=", "avatar_url": "https://avatars.githubusercontent.com/u/1872137?v=4", "gravatar_id": "", "url": "https://api.github.com/users/adashen", "html_url": "https://github.com/adashen", "followers_url": "https://api.github.com/users/adashen/followers", "following_url": "https://api.github.com/users/adashen/following{/other_user}", "gists_url": "https://api.github.com/users/adashen/gists{/gist_id}", "starred_url": "https://api.github.com/users/adashen/starred{/owner}{/repo}", "subscriptions_url": "https://api.github.com/users/adashen/subscriptions", "organizations_url": "https://api.github.com/users/adashen/orgs", "repos_url": "https://api.github.com/users/adashen/repos", "events_url": "https://api.github.com/users/adashen/events{/privacy}", "received_events_url": "https://api.github.com/users/adashen/received_events", "type": "User", "user_view_type": "public", "site_admin": false}, {"login": "adbarlow", "id": 8389570, "node_id": "MDQ6VXNlcjgzODk1NzA=", "avatar_url": "https://avatars.githubusercontent.com/u/8389570?v=4", "gravatar_id": "", "url": "https://api.github.com/users/adbarlow", "html_url": "https://github.com/adbarlow", "followers_url": "https://api.github.com/users/adbarlow/followers", "following_url": "https://api.github.com/users/adbarlow/following{/other_user}", "gists_url": "https://api.github.com/users/adbarlow/gists{/gist_id}", "starred_url": "https://api.github.com/users/adbarlow/starred{/owner}{/repo}", "subscriptions_url": "https://api.github.com/users/adbarlow/subscriptions", "organizations_url": "https://api.github.com/users/adbarlow/orgs", "repos_url": "https://api.github.com/users/adbarlow/repos", "events_url": "https://api.github.com/users/adbarlow/events{/privacy}", "received_events_url": "https://api.github.com/users/adbarlow/received_events", "type": "User", "user_view_type": "public", "site_admin": false}, {"login": "adburch", "id": 25110759, "node_id": "MDQ6VXNlcjI1MTEwNzU5", "avatar_url": "https://avatars.githubusercontent.com/u/25110759?v=4", "gravatar_id": "", "url": "https://api.github.com/users/adburch", "html_url": "https://github.com/adburch", "followers_url": "https://api.github.com/users/adburch/followers", "following_url": "https://api.github.com/users/adburch/following{/other_user}", "gists_url": "https://api.github.com/users/adburch/gists{/gist_id}", "starred_url": "https://api.github.com/users/adburch/starred{/owner}{/repo}", "subscriptions_url": "https://api.github.com/users/adburch/subscriptions", "organizations_url": "https://api.github.com/users/adburch/orgs", "repos_url": "https://api.github.com/users/adburch/repos", "events_url": "https://api.github.com/users/adburch/events{/privacy}", "received_events_url": "https://api.github.com/users/adburch/received_events", "type": "User", "user_view_type": "public", "site_admin": false}, {"login": "adclements", "id": 42748367, "node_id": "MDQ6VXNlcjQyNzQ4MzY3", "avatar_url": "https://avatars.githubusercontent.com/u/42748367?v=4", "gravatar_id": "", "url": "https://api.github.com/users/adclements", "html_url": "https://github.com/adclements", "followers_url": "https://api.github.com/users/adclements/followers", "following_url": "https://api.github.com/users/adclements/following{/other_user}", "gists_url": "https://api.github.com/users/adclements/gists{/gist_id}", "starred_url": "https://api.github.com/users/adclements/starred{/owner}{/repo}", "subscriptions_url": "https://api.github.com/users/adclements/subscriptions", "organizations_url": "https://api.github.com/users/adclements/orgs", "repos_url": "https://api.github.com/users/adclements/repos", "events_url": "https://api.github.com/users/adclements/events{/privacy}", "received_events_url": "https://api.github.com/users/adclements/received_events", "type": "User", "user_view_type": "public", "site_admin": false}, {"login": "adgroc", "id": 12113281, "node_id": "MDQ6VXNlcjEyMTEzMjgx", "avatar_url": "https://avatars.githubusercontent.com/u/12113281?v=4", "gravatar_id": "", "url": "https://api.github.com/users/adgroc", "html_url": "https://github.com/adgroc", "followers_url": "https://api.github.com/users/adgroc/followers", "following_url": "https://api.github.com/users/adgroc/following{/other_user}", "gists_url": "https://api.github.com/users/adgroc/gists{/gist_id}", "starred_url": "https://api.github.com/users/adgroc/starred{/owner}{/repo}", "subscriptions_url": "https://api.github.com/users/adgroc/subscriptions", "organizations_url": "https://api.github.com/users/adgroc/orgs", "repos_url": "https://api.github.com/users/adgroc/repos", "events_url": "https://api.github.com/users/adgroc/events{/privacy}", "received_events_url": "https://api.github.com/users/adgroc/received_events", "type": "User", "user_view_type": "public", "site_admin": false}, {"login": "adhishchugh", "id": 12631567, "node_id": "MDQ6VXNlcjEyNjMxNTY3", "avatar_url": "https://avatars.githubusercontent.com/u/12631567?v=4", "gravatar_id": "", "url": "https://api.github.com/users/adhishchugh", "html_url": "https://github.com/adhishchugh", "followers_url": "https://api.github.com/users/adhishchugh/followers", "following_url": "https://api.github.com/users/adhishchugh/following{/other_user}", "gists_url": "https://api.github.com/users/adhishchugh/gists{/gist_id}", "starred_url": "https://api.github.com/users/adhishchugh/starred{/owner}{/repo}", "subscriptions_url": "https://api.github.com/users/adhishchugh/subscriptions", "organizations_url": "https://api.github.com/users/adhishchugh/orgs", "repos_url": "https://api.github.com/users/adhishchugh/repos", "events_url": "https://api.github.com/users/adhishchugh/events{/privacy}", "received_events_url": "https://api.github.com/users/adhishchugh/received_events", "type": "User", "user_view_type": "public", "site_admin": false}, {"login": "AdinaTru", "id": 2581196, "node_id": "MDQ6VXNlcjI1ODExOTY=", "avatar_url": "https://avatars.githubusercontent.com/u/2581196?v=4", "gravatar_id": "", "url": "https://api.github.com/users/AdinaTru", "html_url": "https://github.com/AdinaTru", "followers_url": "https://api.github.com/users/AdinaTru/followers", "following_url": "https://api.github.com/users/AdinaTru/following{/other_user}", "gists_url": "https://api.github.com/users/AdinaTru/gists{/gist_id}", "starred_url": "https://api.github.com/users/AdinaTru/starred{/owner}{/repo}", "subscriptions_url": "https://api.github.com/users/AdinaTru/subscriptions", "organizations_url": "https://api.github.com/users/AdinaTru/orgs", "repos_url": "https://api.github.com/users/AdinaTru/repos", "events_url": "https://api.github.com/users/AdinaTru/events{/privacy}", "received_events_url": "https://api.github.com/users/AdinaTru/received_events", "type": "User", "user_view_type": "public", "site_admin": false}, {"login": "aditdalvi", "id": 62365436, "node_id": "MDQ6VXNlcjYyMzY1NDM2", "avatar_url": "https://avatars.githubusercontent.com/u/62365436?v=4", "gravatar_id": "", "url": "https://api.github.com/users/aditdalvi", "html_url": "https://github.com/aditdalvi", "followers_url": "https://api.github.com/users/aditdalvi/followers", "following_url": "https://api.github.com/users/aditdalvi/following{/other_user}", "gists_url": "https://api.github.com/users/aditdalvi/gists{/gist_id}", "starred_url": "https://api.github.com/users/aditdalvi/starred{/owner}{/repo}", "subscriptions_url": "https://api.github.com/users/aditdalvi/subscriptions", "organizations_url": "https://api.github.com/users/aditdalvi/orgs", "repos_url": "https://api.github.com/users/aditdalvi/repos", "events_url": "https://api.github.com/users/aditdalvi/events{/privacy}", "received_events_url": "https://api.github.com/users/aditdalvi/received_events", "type": "User", "user_view_type": "public", "site_admin": false}, {"login": "aditya30394", "id": 8336542, "node_id": "MDQ6VXNlcjgzMzY1NDI=", "avatar_url": "https://avatars.githubusercontent.com/u/8336542?v=4", "gravatar_id": "", "url": "https://api.github.com/users/aditya30394", "html_url": "https://github.com/aditya30394", "followers_url": "https://api.github.com/users/aditya30394/followers", "following_url": "https://api.github.com/users/aditya30394/following{/other_user}", "gists_url": "https://api.github.com/users/aditya30394/gists{/gist_id}", "starred_url": "https://api.github.com/users/aditya30394/starred{/owner}{/repo}", "subscriptions_url": "https://api.github.com/users/aditya30394/subscriptions", "organizations_url": "https://api.github.com/users/aditya30394/orgs", "repos_url": "https://api.github.com/users/aditya30394/repos", "events_url": "https://api.github.com/users/aditya30394/events{/privacy}", "received_events_url": "https://api.github.com/users/aditya30394/received_events", "type": "User", "user_view_type": "public", "site_admin": false}, {"login": "adityaj-ms", "id": 33532441, "node_id": "MDQ6VXNlcjMzNTMyNDQx", "avatar_url": "https://avatars.githubusercontent.com/u/33532441?v=4", "gravatar_id": "", "url": "https://api.github.com/users/adityaj-ms", "html_url": "https://github.com/adityaj-ms", "followers_url": "https://api.github.com/users/adityaj-ms/followers", "following_url": "https://api.github.com/users/adityaj-ms/following{/other_user}", "gists_url": "https://api.github.com/users/adityaj-ms/gists{/gist_id}", "starred_url": "https://api.github.com/users/adityaj-ms/starred{/owner}{/repo}", "subscriptions_url": "https://api.github.com/users/adityaj-ms/subscriptions", "organizations_url": "https://api.github.com/users/adityaj-ms/orgs", "repos_url": "https://api.github.com/users/adityaj-ms/repos", "events_url": "https://api.github.com/users/adityaj-ms/events{/privacy}", "received_events_url": "https://api.github.com/users/adityaj-ms/received_events", "type": "User", "user_view_type": "public", "site_admin": false}, {"login": "adityamandaleeka", "id": 219224, "node_id": "MDQ6VXNlcjIxOTIyNA==", "avatar_url": "https://avatars.githubusercontent.com/u/219224?v=4", "gravatar_id": "", "url": "https://api.github.com/users/adityamandaleeka", "html_url": "https://github.com/adityamandaleeka", "followers_url": "https://api.github.com/users/adityamandaleeka/followers", "following_url": "https://api.github.com/users/adityamandaleeka/following{/other_user}", "gists_url": "https://api.github.com/users/adityamandaleeka/gists{/gist_id}", "starred_url": "https://api.github.com/users/adityamandaleeka/starred{/owner}{/repo}", "subscriptions_url": "https://api.github.com/users/adityamandaleeka/subscriptions", "organizations_url": "https://api.github.com/users/adityamandaleeka/orgs", "repos_url": "https://api.github.com/users/adityamandaleeka/repos", "events_url": "https://api.github.com/users/adityamandaleeka/events{/privacy}", "received_events_url": "https://api.github.com/users/adityamandaleeka/received_events", "type": "User", "user_view_type": "public", "site_admin": false}, {"login": "adityapatwardhan", "id": 12820925, "node_id": "MDQ6VXNlcjEyODIwOTI1", "avatar_url": "https://avatars.githubusercontent.com/u/12820925?v=4", "gravatar_id": "", "url": "https://api.github.com/users/adityapatwardhan", "html_url": "https://github.com/adityapatwardhan", "followers_url": "https://api.github.com/users/adityapatwardhan/followers", "following_url": "https://api.github.com/users/adityapatwardhan/following{/other_user}", "gists_url": "https://api.github.com/users/adityapatwardhan/gists{/gist_id}", "starred_url": "https://api.github.com/users/adityapatwardhan/starred{/owner}{/repo}", "subscriptions_url": "https://api.github.com/users/adityapatwardhan/subscriptions", "organizations_url": "https://api.github.com/users/adityapatwardhan/orgs", "repos_url": "https://api.github.com/users/adityapatwardhan/repos", "events_url": "https://api.github.com/users/adityapatwardhan/events{/privacy}", "received_events_url": "https://api.github.com/users/adityapatwardhan/received_events", "type": "User", "user_view_type": "public", "site_admin": false}, {"login": "adityareddy305", "id": 20465811, "node_id": "MDQ6VXNlcjIwNDY1ODEx", "avatar_url": "https://avatars.githubusercontent.com/u/20465811?v=4", "gravatar_id": "", "url": "https://api.github.com/users/adityareddy305", "html_url": "https://github.com/adityareddy305", "followers_url": "https://api.github.com/users/adityareddy305/followers", "following_url": "https://api.github.com/users/adityareddy305/following{/other_user}", "gists_url": "https://api.github.com/users/adityareddy305/gists{/gist_id}", "starred_url": "https://api.github.com/users/adityareddy305/starred{/owner}{/repo}", "subscriptions_url": "https://api.github.com/users/adityareddy305/subscriptions", "organizations_url": "https://api.github.com/users/adityareddy305/orgs", "repos_url": "https://api.github.com/users/adityareddy305/repos", "events_url": "https://api.github.com/users/adityareddy305/events{/privacy}", "received_events_url": "https://api.github.com/users/adityareddy305/received_events", "type": "User", "user_view_type": "public", "site_admin": false}, {"login": "adityatMS", "id": 23708375, "node_id": "MDQ6VXNlcjIzNzA4Mzc1", "avatar_url": "https://avatars.githubusercontent.com/u/23708375?v=4", "gravatar_id": "", "url": "https://api.github.com/users/adityatMS", "html_url": "https://github.com/adityatMS", "followers_url": "https://api.github.com/users/adityatMS/followers", "following_url": "https://api.github.com/users/adityatMS/following{/other_user}", "gists_url": "https://api.github.com/users/adityatMS/gists{/gist_id}", "starred_url": "https://api.github.com/users/adityatMS/starred{/owner}{/repo}", "subscriptions_url": "https://api.github.com/users/adityatMS/subscriptions", "organizations_url": "https://api.github.com/users/adityatMS/orgs", "repos_url": "https://api.github.com/users/adityatMS/repos", "events_url": "https://api.github.com/users/adityatMS/events{/privacy}", "received_events_url": "https://api.github.com/users/adityatMS/received_events", "type": "User", "user_view_type": "public", "site_admin": false}, {"login": "adkhandelwal149", "id": 226493145, "node_id": "U_kgDODYAC2Q", "avatar_url": "https://avatars.githubusercontent.com/u/226493145?v=4", "gravatar_id": "", "url": "https://api.github.com/users/adkhandelwal149", "html_url": "https://github.com/adkhandelwal149", "followers_url": "https://api.github.com/users/adkhandelwal149/followers", "following_url": "https://api.github.com/users/adkhandelwal149/following{/other_user}", "gists_url": "https://api.github.com/users/adkhandelwal149/gists{/gist_id}", "starred_url": "https://api.github.com/users/adkhandelwal149/starred{/owner}{/repo}", "subscriptions_url": "https://api.github.com/users/adkhandelwal149/subscriptions", "organizations_url": "https://api.github.com/users/adkhandelwal149/orgs", "repos_url": "https://api.github.com/users/adkhandelwal149/repos", "events_url": "https://api.github.com/users/adkhandelwal149/events{/privacy}", "received_events_url": "https://api.github.com/users/adkhandelwal149/received_events", "type": "User", "user_view_type": "public", "site_admin": false}, {"login": "admayber", "id": 44822281, "node_id": "MDQ6VXNlcjQ0ODIyMjgx", "avatar_url": "https://avatars.githubusercontent.com/u/44822281?v=4", "gravatar_id": "", "url": "https://api.github.com/users/admayber", "html_url": "https://github.com/admayber", "followers_url": "https://api.github.com/users/admayber/followers", "following_url": "https://api.github.com/users/admayber/following{/other_user}", "gists_url": "https://api.github.com/users/admayber/gists{/gist_id}", "starred_url": "https://api.github.com/users/admayber/starred{/owner}{/repo}", "subscriptions_url": "https://api.github.com/users/admayber/subscriptions", "organizations_url": "https://api.github.com/users/admayber/orgs", "repos_url": "https://api.github.com/users/admayber/repos", "events_url": "https://api.github.com/users/admayber/events{/privacy}", "received_events_url": "https://api.github.com/users/admayber/received_events", "type": "User", "user_view_type": "public", "site_admin": false}, {"login": "ADobin", "id": 1153715, "node_id": "MDQ6VXNlcjExNTM3MTU=", "avatar_url": "https://avatars.githubusercontent.com/u/1153715?v=4", "gravatar_id": "", "url": "https://api.github.com/users/ADobin", "html_url": "https://github.com/ADobin", "followers_url": "https://api.github.com/users/ADobin/followers", "following_url": "https://api.github.com/users/ADobin/following{/other_user}", "gists_url": "https://api.github.com/users/ADobin/gists{/gist_id}", "starred_url": "https://api.github.com/users/ADobin/starred{/owner}{/repo}", "subscriptions_url": "https://api.github.com/users/ADobin/subscriptions", "organizations_url": "https://api.github.com/users/ADobin/orgs", "repos_url": "https://api.github.com/users/ADobin/repos", "events_url": "https://api.github.com/users/ADobin/events{/privacy}", "received_events_url": "https://api.github.com/users/ADobin/received_events", "type": "User", "user_view_type": "public", "site_admin": false}, {"login": "adonis-ms", "id": 185483635, "node_id": "U_kgDOCw5Bcw", "avatar_url": "https://avatars.githubusercontent.com/u/185483635?v=4", "gravatar_id": "", "url": "https://api.github.com/users/adonis-ms", "html_url": "https://github.com/adonis-ms", "followers_url": "https://api.github.com/users/adonis-ms/followers", "following_url": "https://api.github.com/users/adonis-ms/following{/other_user}", "gists_url": "https://api.github.com/users/adonis-ms/gists{/gist_id}", "starred_url": "https://api.github.com/users/adonis-ms/starred{/owner}{/repo}", "subscriptions_url": "https://api.github.com/users/adonis-ms/subscriptions", "organizations_url": "https://api.github.com/users/adonis-ms/orgs", "repos_url": "https://api.github.com/users/adonis-ms/repos", "events_url": "https://api.github.com/users/adonis-ms/events{/privacy}", "received_events_url": "https://api.github.com/users/adonis-ms/received_events", "type": "User", "user_view_type": "public", "site_admin": false}, {"login": "adrian-leonard-radu", "id": 14207525, "node_id": "MDQ6VXNlcjE0MjA3NTI1", "avatar_url": "https://avatars.githubusercontent.com/u/14207525?v=4", "gravatar_id": "", "url": "https://api.github.com/users/adrian-leonard-radu", "html_url": "https://github.com/adrian-leonard-radu", "followers_url": "https://api.github.com/users/adrian-leonard-radu/followers", "following_url": "https://api.github.com/users/adrian-leonard-radu/following{/other_user}", "gists_url": "https://api.github.com/users/adrian-leonard-radu/gists{/gist_id}", "starred_url": "https://api.github.com/users/adrian-leonard-radu/starred{/owner}{/repo}", "subscriptions_url": "https://api.github.com/users/adrian-leonard-radu/subscriptions", "organizations_url": "https://api.github.com/users/adrian-leonard-radu/orgs", "repos_url": "https://api.github.com/users/adrian-leonard-radu/repos", "events_url": "https://api.github.com/users/adrian-leonard-radu/events{/privacy}", "received_events_url": "https://api.github.com/users/adrian-leonard-radu/received_events", "type": "User", "user_view_type": "public", "site_admin": false}, {"login": "Adrian-Zhang", "id": 67034199, "node_id": "MDQ6VXNlcjY3MDM0MTk5", "avatar_url": "https://avatars.githubusercontent.com/u/67034199?v=4", "gravatar_id": "", "url": "https://api.github.com/users/Adrian-Zhang", "html_url": "https://github.com/Adrian-Zhang", "followers_url": "https://api.github.com/users/Adrian-Zhang/followers", "following_url": "https://api.github.com/users/Adrian-Zhang/following{/other_user}", "gists_url": "https://api.github.com/users/Adrian-Zhang/gists{/gist_id}", "starred_url": "https://api.github.com/users/Adrian-Zhang/starred{/owner}{/repo}", "subscriptions_url": "https://api.github.com/users/Adrian-Zhang/subscriptions", "organizations_url": "https://api.github.com/users/Adrian-Zhang/orgs", "repos_url": "https://api.github.com/users/Adrian-Zhang/repos", "events_url": "https://api.github.com/users/Adrian-Zhang/events{/privacy}", "received_events_url": "https://api.github.com/users/Adrian-Zhang/received_events", "type": "User", "user_view_type": "public", "site_admin": false}, {"login": "AdrianBZG", "id": 8275330, "node_id": "MDQ6VXNlcjgyNzUzMzA=", "avatar_url": "https://avatars.githubusercontent.com/u/8275330?v=4", "gravatar_id": "", "url": "https://api.github.com/users/AdrianBZG", "html_url": "https://github.com/AdrianBZG", "followers_url": "https://api.github.com/users/AdrianBZG/followers", "following_url": "https://api.github.com/users/AdrianBZG/following{/other_user}", "gists_url": "https://api.github.com/users/AdrianBZG/gists{/gist_id}", "starred_url": "https://api.github.com/users/AdrianBZG/starred{/owner}{/repo}", "subscriptions_url": "https://api.github.com/users/AdrianBZG/subscriptions", "organizations_url": "https://api.github.com/users/AdrianBZG/orgs", "repos_url": "https://api.github.com/users/AdrianBZG/repos", "events_url": "https://api.github.com/users/AdrianBZG/events{/privacy}", "received_events_url": "https://api.github.com/users/AdrianBZG/received_events", "type": "User", "user_view_type": "public", "site_admin": false}, {"login": "adrianlavery", "id": 10516779, "node_id": "MDQ6VXNlcjEwNTE2Nzc5", "avatar_url": "https://avatars.githubusercontent.com/u/10516779?v=4", "gravatar_id": "", "url": "https://api.github.com/users/adrianlavery", "html_url": "https://github.com/adrianlavery", "followers_url": "https://api.github.com/users/adrianlavery/followers", "following_url": "https://api.github.com/users/adrianlavery/following{/other_user}", "gists_url": "https://api.github.com/users/adrianlavery/gists{/gist_id}", "starred_url": "https://api.github.com/users/adrianlavery/starred{/owner}{/repo}", "subscriptions_url": "https://api.github.com/users/adrianlavery/subscriptions", "organizations_url": "https://api.github.com/users/adrianlavery/orgs", "repos_url": "https://api.github.com/users/adrianlavery/repos", "events_url": "https://api.github.com/users/adrianlavery/events{/privacy}", "received_events_url": "https://api.github.com/users/adrianlavery/received_events", "type": "User", "user_view_type": "public", "site_admin": false}, {"login": "adrianmg", "id": 589285, "node_id": "MDQ6VXNlcjU4OTI4NQ==", "avatar_url": "https://avatars.githubusercontent.com/u/589285?v=4", "gravatar_id": "", "url": "https://api.github.com/users/adrianmg", "html_url": "https://github.com/adrianmg", "followers_url": "https://api.github.com/users/adrianmg/followers", "following_url": "https://api.github.com/users/adrianmg/following{/other_user}", "gists_url": "https://api.github.com/users/adrianmg/gists{/gist_id}", "starred_url": "https://api.github.com/users/adrianmg/starred{/owner}{/repo}", "subscriptions_url": "https://api.github.com/users/adrianmg/subscriptions", "organizations_url": "https://api.github.com/users/adrianmg/orgs", "repos_url": "https://api.github.com/users/adrianmg/repos", "events_url": "https://api.github.com/users/adrianmg/events{/privacy}", "received_events_url": "https://api.github.com/users/adrianmg/received_events", "type": "User", "user_view_type": "public", "site_admin": true}, {"login": "adrianmo", "id": 3786750, "node_id": "MDQ6VXNlcjM3ODY3NTA=", "avatar_url": "https://avatars.githubusercontent.com/u/3786750?v=4", "gravatar_id": "", "url": "https://api.github.com/users/adrianmo", "html_url": "https://github.com/adrianmo", "followers_url": "https://api.github.com/users/adrianmo/followers", "following_url": "https://api.github.com/users/adrianmo/following{/other_user}", "gists_url": "https://api.github.com/users/adrianmo/gists{/gist_id}", "starred_url": "https://api.github.com/users/adrianmo/starred{/owner}{/repo}", "subscriptions_url": "https://api.github.com/users/adrianmo/subscriptions", "organizations_url": "https://api.github.com/users/adrianmo/orgs", "repos_url": "https://api.github.com/users/adrianmo/repos", "events_url": "https://api.github.com/users/adrianmo/events{/privacy}", "received_events_url": "https://api.github.com/users/adrianmo/received_events", "type": "User", "user_view_type": "public", "site_admin": false}, {"login": "adrianorth", "id": 22684724, "node_id": "MDQ6VXNlcjIyNjg0NzI0", "avatar_url": "https://avatars.githubusercontent.com/u/22684724?v=4", "gravatar_id": "", "url": "https://api.github.com/users/adrianorth", "html_url": "https://github.com/adrianorth", "followers_url": "https://api.github.com/users/adrianorth/followers", "following_url": "https://api.github.com/users/adrianorth/following{/other_user}", "gists_url": "https://api.github.com/users/adrianorth/gists{/gist_id}", "starred_url": "https://api.github.com/users/adrianorth/starred{/owner}{/repo}", "subscriptions_url": "https://api.github.com/users/adrianorth/subscriptions", "organizations_url": "https://api.github.com/users/adrianorth/orgs", "repos_url": "https://api.github.com/users/adrianorth/repos", "events_url": "https://api.github.com/users/adrianorth/events{/privacy}", "received_events_url": "https://api.github.com/users/adrianorth/received_events", "type": "User", "user_view_type": "public", "site_admin": false}, {"login": "adrianvmsft", "id": 12467530, "node_id": "MDQ6VXNlcjEyNDY3NTMw", "avatar_url": "https://avatars.githubusercontent.com/u/12467530?v=4", "gravatar_id": "", "url": "https://api.github.com/users/adrianvmsft", "html_url": "https://github.com/adrianvmsft", "followers_url": "https://api.github.com/users/adrianvmsft/followers", "following_url": "https://api.github.com/users/adrianvmsft/following{/other_user}", "gists_url": "https://api.github.com/users/adrianvmsft/gists{/gist_id}", "starred_url": "https://api.github.com/users/adrianvmsft/starred{/owner}{/repo}", "subscriptions_url": "https://api.github.com/users/adrianvmsft/subscriptions", "organizations_url": "https://api.github.com/users/adrianvmsft/orgs", "repos_url": "https://api.github.com/users/adrianvmsft/repos", "events_url": "https://api.github.com/users/adrianvmsft/events{/privacy}", "received_events_url": "https://api.github.com/users/adrianvmsft/received_events", "type": "User", "user_view_type": "public", "site_admin": false}, {"login": "adrientoub", "id": 2855956, "node_id": "MDQ6VXNlcjI4NTU5NTY=", "avatar_url": "https://avatars.githubusercontent.com/u/2855956?v=4", "gravatar_id": "", "url": "https://api.github.com/users/adrientoub", "html_url": "https://github.com/adrientoub", "followers_url": "https://api.github.com/users/adrientoub/followers", "following_url": "https://api.github.com/users/adrientoub/following{/other_user}", "gists_url": "https://api.github.com/users/adrientoub/gists{/gist_id}", "starred_url": "https://api.github.com/users/adrientoub/starred{/owner}{/repo}", "subscriptions_url": "https://api.github.com/users/adrientoub/subscriptions", "organizations_url": "https://api.github.com/users/adrientoub/orgs", "repos_url": "https://api.github.com/users/adrientoub/repos", "events_url": "https://api.github.com/users/adrientoub/events{/privacy}", "received_events_url": "https://api.github.com/users/adrientoub/received_events", "type": "User", "user_view_type": "public", "site_admin": false}, {"login": "adyabansal-ms", "id": 203599301, "node_id": "U_kgDODCKtxQ", "avatar_url": "https://avatars.githubusercontent.com/u/203599301?v=4", "gravatar_id": "", "url": "https://api.github.com/users/adyabansal-ms", "html_url": "https://github.com/adyabansal-ms", "followers_url": "https://api.github.com/users/adyabansal-ms/followers", "following_url": "https://api.github.com/users/adyabansal-ms/following{/other_user}", "gists_url": "https://api.github.com/users/adyabansal-ms/gists{/gist_id}", "starred_url": "https://api.github.com/users/adyabansal-ms/starred{/owner}{/repo}", "subscriptions_url": "https://api.github.com/users/adyabansal-ms/subscriptions", "organizations_url": "https://api.github.com/users/adyabansal-ms/orgs", "repos_url": "https://api.github.com/users/adyabansal-ms/repos", "events_url": "https://api.github.com/users/adyabansal-ms/events{/privacy}", "received_events_url": "https://api.github.com/users/adyabansal-ms/received_events", "type": "User", "user_view_type": "public", "site_admin": false}, {"login": "aef123", "id": 3704736, "node_id": "MDQ6VXNlcjM3MDQ3MzY=", "avatar_url": "https://avatars.githubusercontent.com/u/3704736?v=4", "gravatar_id": "", "url": "https://api.github.com/users/aef123", "html_url": "https://github.com/aef123", "followers_url": "https://api.github.com/users/aef123/followers", "following_url": "https://api.github.com/users/aef123/following{/other_user}", "gists_url": "https://api.github.com/users/aef123/gists{/gist_id}", "starred_url": "https://api.github.com/users/aef123/starred{/owner}{/repo}", "subscriptions_url": "https://api.github.com/users/aef123/subscriptions", "organizations_url": "https://api.github.com/users/aef123/orgs", "repos_url": "https://api.github.com/users/aef123/repos", "events_url": "https://api.github.com/users/aef123/events{/privacy}", "received_events_url": "https://api.github.com/users/aef123/received_events", "type": "User", "user_view_type": "public", "site_admin": false}, {"login": "aelij", "id": 496737, "node_id": "MDQ6VXNlcjQ5NjczNw==", "avatar_url": "https://avatars.githubusercontent.com/u/496737?v=4", "gravatar_id": "", "url": "https://api.github.com/users/aelij", "html_url": "https://github.com/aelij", "followers_url": "https://api.github.com/users/aelij/followers", "following_url": "https://api.github.com/users/aelij/following{/other_user}", "gists_url": "https://api.github.com/users/aelij/gists{/gist_id}", "starred_url": "https://api.github.com/users/aelij/starred{/owner}{/repo}", "subscriptions_url": "https://api.github.com/users/aelij/subscriptions", "organizations_url": "https://api.github.com/users/aelij/orgs", "repos_url": "https://api.github.com/users/aelij/repos", "events_url": "https://api.github.com/users/aelij/events{/privacy}", "received_events_url": "https://api.github.com/users/aelij/received_events", "type": "User", "user_view_type": "public", "site_admin": false}, {"login": "aessing", "id": 21235652, "node_id": "MDQ6VXNlcjIxMjM1NjUy", "avatar_url": "https://avatars.githubusercontent.com/u/21235652?v=4", "gravatar_id": "", "url": "https://api.github.com/users/aessing", "html_url": "https://github.com/aessing", "followers_url": "https://api.github.com/users/aessing/followers", "following_url": "https://api.github.com/users/aessing/following{/other_user}", "gists_url": "https://api.github.com/users/aessing/gists{/gist_id}", "starred_url": "https://api.github.com/users/aessing/starred{/owner}{/repo}", "subscriptions_url": "https://api.github.com/users/aessing/subscriptions", "organizations_url": "https://api.github.com/users/aessing/orgs", "repos_url": "https://api.github.com/users/aessing/repos", "events_url": "https://api.github.com/users/aessing/events{/privacy}", "received_events_url": "https://api.github.com/users/aessing/received_events", "type": "User", "user_view_type": "public", "site_admin": false}, {"login": "afilenkov", "id": 28574821, "node_id": "MDQ6VXNlcjI4NTc0ODIx", "avatar_url": "https://avatars.githubusercontent.com/u/28574821?v=4", "gravatar_id": "", "url": "https://api.github.com/users/afilenkov", "html_url": "https://github.com/afilenkov", "followers_url": "https://api.github.com/users/afilenkov/followers", "following_url": "https://api.github.com/users/afilenkov/following{/other_user}", "gists_url": "https://api.github.com/users/afilenkov/gists{/gist_id}", "starred_url": "https://api.github.com/users/afilenkov/starred{/owner}{/repo}", "subscriptions_url": "https://api.github.com/users/afilenkov/subscriptions", "organizations_url": "https://api.github.com/users/afilenkov/orgs", "repos_url": "https://api.github.com/users/afilenkov/repos", "events_url": "https://api.github.com/users/afilenkov/events{/privacy}", "received_events_url": "https://api.github.com/users/afilenkov/received_events", "type": "User", "user_view_type": "public", "site_admin": false}, {"login": "afourney", "id": 4017093, "node_id": "MDQ6VXNlcjQwMTcwOTM=", "avatar_url": "https://avatars.githubusercontent.com/u/4017093?v=4", "gravatar_id": "", "url": "https://api.github.com/users/afourney", "html_url": "https://github.com/afourney", "followers_url": "https://api.github.com/users/afourney/followers", "following_url": "https://api.github.com/users/afourney/following{/other_user}", "gists_url": "https://api.github.com/users/afourney/gists{/gist_id}", "starred_url": "https://api.github.com/users/afourney/starred{/owner}{/repo}", "subscriptions_url": "https://api.github.com/users/afourney/subscriptions", "organizations_url": "https://api.github.com/users/afourney/orgs", "repos_url": "https://api.github.com/users/afourney/repos", "events_url": "https://api.github.com/users/afourney/events{/privacy}", "received_events_url": "https://api.github.com/users/afourney/received_events", "type": "User", "user_view_type": "public", "site_admin": false}, {"login": "afshinm", "id": 314326, "node_id": "MDQ6VXNlcjMxNDMyNg==", "avatar_url": "https://avatars.githubusercontent.com/u/314326?v=4", "gravatar_id": "", "url": "https://api.github.com/users/afshinm", "html_url": "https://github.com/afshinm", "followers_url": "https://api.github.com/users/afshinm/followers", "following_url": "https://api.github.com/users/afshinm/following{/other_user}", "gists_url": "https://api.github.com/users/afshinm/gists{/gist_id}", "starred_url": "https://api.github.com/users/afshinm/starred{/owner}{/repo}", "subscriptions_url": "https://api.github.com/users/afshinm/subscriptions", "organizations_url": "https://api.github.com/users/afshinm/orgs", "repos_url": "https://api.github.com/users/afshinm/repos", "events_url": "https://api.github.com/users/afshinm/events{/privacy}", "received_events_url": "https://api.github.com/users/afshinm/received_events", "type": "User", "user_view_type": "public", "site_admin": false}, {"login": "AfstoneBharfon", "id": 106490968, "node_id": "U_kgDOBljsWA", "avatar_url": "https://avatars.githubusercontent.com/u/106490968?v=4", "gravatar_id": "", "url": "https://api.github.com/users/AfstoneBharfon", "html_url": "https://github.com/AfstoneBharfon", "followers_url": "https://api.github.com/users/AfstoneBharfon/followers", "following_url": "https://api.github.com/users/AfstoneBharfon/following{/other_user}", "gists_url": "https://api.github.com/users/AfstoneBharfon/gists{/gist_id}", "starred_url": "https://api.github.com/users/AfstoneBharfon/starred{/owner}{/repo}", "subscriptions_url": "https://api.github.com/users/AfstoneBharfon/subscriptions", "organizations_url": "https://api.github.com/users/AfstoneBharfon/orgs", "repos_url": "https://api.github.com/users/AfstoneBharfon/repos", "events_url": "https://api.github.com/users/AfstoneBharfon/events{/privacy}", "received_events_url": "https://api.github.com/users/AfstoneBharfon/received_events", "type": "User", "user_view_type": "public", "site_admin": false}, {"login": "ag6221254", "id": 102785977, "node_id": "U_kgDOBiBjuQ", "avatar_url": "https://avatars.githubusercontent.com/u/102785977?v=4", "gravatar_id": "", "url": "https://api.github.com/users/ag6221254", "html_url": "https://github.com/ag6221254", "followers_url": "https://api.github.com/users/ag6221254/followers", "following_url": "https://api.github.com/users/ag6221254/following{/other_user}", "gists_url": "https://api.github.com/users/ag6221254/gists{/gist_id}", "starred_url": "https://api.github.com/users/ag6221254/starred{/owner}{/repo}", "subscriptions_url": "https://api.github.com/users/ag6221254/subscriptions", "organizations_url": "https://api.github.com/users/ag6221254/orgs", "repos_url": "https://api.github.com/users/ag6221254/repos", "events_url": "https://api.github.com/users/ag6221254/events{/privacy}", "received_events_url": "https://api.github.com/users/ag6221254/received_events", "type": "User", "user_view_type": "public", "site_admin": false}, {"login": "agambo", "id": 17580198, "node_id": "MDQ6VXNlcjE3NTgwMTk4", "avatar_url": "https://avatars.githubusercontent.com/u/17580198?v=4", "gravatar_id": "", "url": "https://api.github.com/users/agambo", "html_url": "https://github.com/agambo", "followers_url": "https://api.github.com/users/agambo/followers", "following_url": "https://api.github.com/users/agambo/following{/other_user}", "gists_url": "https://api.github.com/users/agambo/gists{/gist_id}", "starred_url": "https://api.github.com/users/agambo/starred{/owner}{/repo}", "subscriptions_url": "https://api.github.com/users/agambo/subscriptions", "organizations_url": "https://api.github.com/users/agambo/orgs", "repos_url": "https://api.github.com/users/agambo/repos", "events_url": "https://api.github.com/users/agambo/events{/privacy}", "received_events_url": "https://api.github.com/users/agambo/received_events", "type": "User", "user_view_type": "public", "site_admin": false}, {"login": "AgentEpsilon", "id": 5257035, "node_id": "MDQ6VXNlcjUyNTcwMzU=", "avatar_url": "https://avatars.githubusercontent.com/u/5257035?v=4", "gravatar_id": "", "url": "https://api.github.com/users/AgentEpsilon", "html_url": "https://github.com/AgentEpsilon", "followers_url": "https://api.github.com/users/AgentEpsilon/followers", "following_url": "https://api.github.com/users/AgentEpsilon/following{/other_user}", "gists_url": "https://api.github.com/users/AgentEpsilon/gists{/gist_id}", "starred_url": "https://api.github.com/users/AgentEpsilon/starred{/owner}{/repo}", "subscriptions_url": "https://api.github.com/users/AgentEpsilon/subscriptions", "organizations_url": "https://api.github.com/users/AgentEpsilon/orgs", "repos_url": "https://api.github.com/users/AgentEpsilon/repos", "events_url": "https://api.github.com/users/AgentEpsilon/events{/privacy}", "received_events_url": "https://api.github.com/users/AgentEpsilon/received_events", "type": "User", "user_view_type": "public", "site_admin": false}, {"login": "aggarwalsw", "id": 186795611, "node_id": "U_kgDOCyJGWw", "avatar_url": "https://avatars.githubusercontent.com/u/186795611?v=4", "gravatar_id": "", "url": "https://api.github.com/users/aggarwalsw", "html_url": "https://github.com/aggarwalsw", "followers_url": "https://api.github.com/users/aggarwalsw/followers", "following_url": "https://api.github.com/users/aggarwalsw/following{/other_user}", "gists_url": "https://api.github.com/users/aggarwalsw/gists{/gist_id}", "starred_url": "https://api.github.com/users/aggarwalsw/starred{/owner}{/repo}", "subscriptions_url": "https://api.github.com/users/aggarwalsw/subscriptions", "organizations_url": "https://api.github.com/users/aggarwalsw/orgs", "repos_url": "https://api.github.com/users/aggarwalsw/repos", "events_url": "https://api.github.com/users/aggarwalsw/events{/privacy}", "received_events_url": "https://api.github.com/users/aggarwalsw/received_events", "type": "User", "user_view_type": "public", "site_admin": false}, {"login": "agocke", "id": 515774, "node_id": "MDQ6VXNlcjUxNTc3NA==", "avatar_url": "https://avatars.githubusercontent.com/u/515774?v=4", "gravatar_id": "", "url": "https://api.github.com/users/agocke", "html_url": "https://github.com/agocke", "followers_url": "https://api.github.com/users/agocke/followers", "following_url": "https://api.github.com/users/agocke/following{/other_user}", "gists_url": "https://api.github.com/users/agocke/gists{/gist_id}", "starred_url": "https://api.github.com/users/agocke/starred{/owner}{/repo}", "subscriptions_url": "https://api.github.com/users/agocke/subscriptions", "organizations_url": "https://api.github.com/users/agocke/orgs", "repos_url": "https://api.github.com/users/agocke/repos", "events_url": "https://api.github.com/users/agocke/events{/privacy}", "received_events_url": "https://api.github.com/users/agocke/received_events", "type": "User", "user_view_type": "public", "site_admin": false}, {"login": "agoncal", "id": 729277, "node_id": "MDQ6VXNlcjcyOTI3Nw==", "avatar_url": "https://avatars.githubusercontent.com/u/729277?v=4", "gravatar_id": "", "url": "https://api.github.com/users/agoncal", "html_url": "https://github.com/agoncal", "followers_url": "https://api.github.com/users/agoncal/followers", "following_url": "https://api.github.com/users/agoncal/following{/other_user}", "gists_url": "https://api.github.com/users/agoncal/gists{/gist_id}", "starred_url": "https://api.github.com/users/agoncal/starred{/owner}{/repo}", "subscriptions_url": "https://api.github.com/users/agoncal/subscriptions", "organizations_url": "https://api.github.com/users/agoncal/orgs", "repos_url": "https://api.github.com/users/agoncal/repos", "events_url": "https://api.github.com/users/agoncal/events{/privacy}", "received_events_url": "https://api.github.com/users/agoncal/received_events", "type": "User", "user_view_type": "public", "site_admin": false}, {"login": "agsanderss", "id": 45366153, "node_id": "MDQ6VXNlcjQ1MzY2MTUz", "avatar_url": "https://avatars.githubusercontent.com/u/45366153?v=4", "gravatar_id": "", "url": "https://api.github.com/users/agsanderss", "html_url": "https://github.com/agsanderss", "followers_url": "https://api.github.com/users/agsanderss/followers", "following_url": "https://api.github.com/users/agsanderss/following{/other_user}", "gists_url": "https://api.github.com/users/agsanderss/gists{/gist_id}", "starred_url": "https://api.github.com/users/agsanderss/starred{/owner}{/repo}", "subscriptions_url": "https://api.github.com/users/agsanderss/subscriptions", "organizations_url": "https://api.github.com/users/agsanderss/orgs", "repos_url": "https://api.github.com/users/agsanderss/repos", "events_url": "https://api.github.com/users/agsanderss/events{/privacy}", "received_events_url": "https://api.github.com/users/agsanderss/received_events", "type": "User", "user_view_type": "public", "site_admin": false}]